{".class":"MypyFile","_fullname":"pyteal.ast.assert_","future_import_flags":[],"is_partial_stub_package":false,"is_stub":false,"names":{".class":"SymbolTable","Assert":{".class":"SymbolTableNode","kind":"Gdef","node":{".class":"TypeInfo","_promote":[],"abstract_attributes":[],"alt_promote":null,"bases":["pyteal.ast.expr.Expr"],"dataclass_transform_spec":null,"declared_metaclass":null,"defn":{".class":"ClassDef","fullname":"pyteal.ast.assert_.Assert","name":"Assert","type_vars":[]},"deletable_attributes":[],"flags":[],"fullname":"pyteal.ast.assert_.Assert","has_param_spec_type":false,"metaclass_type":"abc.ABCMeta","metadata":{},"module_name":"pyteal.ast.assert_","mro":["pyteal.ast.assert_.Assert","pyteal.ast.expr.Expr","abc.ABC","builtins.object"],"names":{".class":"SymbolTable","__init__":{".class":"SymbolTableNode","kind":"Mdef","node":{".class":"FuncDef","abstract_status":0,"arg_kinds":[0,0,2,5],"arg_names":["self","cond","additional_conds","comment"],"dataclass_transform_spec":null,"flags":[],"fullname":"pyteal.ast.assert_.Assert.__init__","name":"__init__","type":{".class":"CallableType","arg_kinds":[0,0,2,5],"arg_names":["self","cond","additional_conds","comment"],"arg_types":["pyteal.ast.assert_.Assert","pyteal.ast.expr.Expr","pyteal.ast.expr.Expr",{".class":"UnionType","items":["builtins.str",{".class":"NoneType"}]}],"bound_args":[],"def_extras":{"first_arg":"self"},"fallback":"builtins.function","from_concatenate":false,"implicit":false,"imprecise_arg_kinds":false,"is_ellipsis_args":false,"name":"__init__ of Assert","ret_type":{".class":"NoneType"},"type_guard":null,"unpack_kwargs":false,"variables":[]}}},"__str__":{".class":"SymbolTableNode","kind":"Mdef","node":{".class":"FuncDef","abstract_status":0,"arg_kinds":[0],"arg_names":[null],"dataclass_transform_spec":null,"flags":[],"fullname":"pyteal.ast.assert_.Assert.__str__","name":"__str__","type":null}},"__teal__":{".class":"SymbolTableNode","kind":"Mdef","node":{".class":"FuncDef","abstract_status":0,"arg_kinds":[0,0],"arg_names":["self","options"],"dataclass_transform_spec":null,"flags":[],"fullname":"pyteal.ast.assert_.Assert.__teal__","name":"__teal__","type":{".class":"CallableType","arg_kinds":[0,0],"arg_names":["self","options"],"arg_types":["pyteal.ast.assert_.Assert","pyteal.compiler.compiler.CompileOptions"],"bound_args":[],"def_extras":{"first_arg":"self"},"fallback":"builtins.function","from_concatenate":false,"implicit":false,"imprecise_arg_kinds":false,"is_ellipsis_args":false,"name":"__teal__ of Assert","ret_type":{".class":"AnyType","missing_import_name":null,"source_any":null,"type_of_any":1},"type_guard":null,"unpack_kwargs":false,"variables":[]}}},"_sframes_container":{".class":"SymbolTableNode","implicit":true,"kind":"Mdef","node":{".class":"Var","flags":["explicit_self_type","is_ready","is_inferred"],"fullname":"pyteal.ast.assert_.Assert._sframes_container","name":"_sframes_container","type":{".class":"UnionType","items":["pyteal.ast.expr.Expr",{".class":"NoneType"}]}}},"comment":{".class":"SymbolTableNode","implicit":true,"kind":"Mdef","node":{".class":"Var","flags":["is_inferred"],"fullname":"pyteal.ast.assert_.Assert.comment","name":"comment","type":{".class":"UnionType","items":["builtins.str",{".class":"NoneType"}]}}},"cond":{".class":"SymbolTableNode","implicit":true,"kind":"Mdef","node":{".class":"Var","flags":["is_inferred"],"fullname":"pyteal.ast.assert_.Assert.cond","name":"cond","type":{".class":"Instance","args":["pyteal.ast.expr.Expr"],"type_ref":"builtins.list"}}},"has_return":{".class":"SymbolTableNode","kind":"Mdef","node":{".class":"FuncDef","abstract_status":0,"arg_kinds":[0],"arg_names":["self"],"dataclass_transform_spec":null,"flags":[],"fullname":"pyteal.ast.assert_.Assert.has_return","name":"has_return","type":null}},"type_of":{".class":"SymbolTableNode","kind":"Mdef","node":{".class":"FuncDef","abstract_status":0,"arg_kinds":[0],"arg_names":["self"],"dataclass_transform_spec":null,"flags":[],"fullname":"pyteal.ast.assert_.Assert.type_of","name":"type_of","type":null}}},"self_type":{".class":"TypeVarType","default":{".class":"AnyType","missing_import_name":null,"source_any":null,"type_of_any":4},"fullname":"pyteal.ast.assert_.Assert.Self","id":0,"name":"Self","namespace":"","upper_bound":"pyteal.ast.assert_.Assert","values":[],"variance":0},"slots":null,"tuple_type":null,"type_vars":[],"typeddict_type":null}},"Comment":{".class":"SymbolTableNode","cross_ref":"pyteal.ast.comment.Comment","kind":"Gdef"},"CompileOptions":{".class":"SymbolTableNode","cross_ref":"pyteal.compiler.compiler.CompileOptions","kind":"Gdef"},"Expr":{".class":"SymbolTableNode","cross_ref":"pyteal.ast.expr.Expr","kind":"Gdef"},"Op":{".class":"SymbolTableNode","cross_ref":"pyteal.ir.ops.Op","kind":"Gdef"},"Seq":{".class":"SymbolTableNode","cross_ref":"pyteal.ast.seq.Seq","kind":"Gdef"},"TYPE_CHECKING":{".class":"SymbolTableNode","cross_ref":"typing.TYPE_CHECKING","kind":"Gdef"},"TealBlock":{".class":"SymbolTableNode","cross_ref":"pyteal.ir.tealblock.TealBlock","kind":"Gdef"},"TealConditionalBlock":{".class":"SymbolTableNode","cross_ref":"pyteal.ir.tealconditionalblock.TealConditionalBlock","kind":"Gdef"},"TealOp":{".class":"SymbolTableNode","cross_ref":"pyteal.ir.tealop.TealOp","kind":"Gdef"},"TealSimpleBlock":{".class":"SymbolTableNode","cross_ref":"pyteal.ir.tealsimpleblock.TealSimpleBlock","kind":"Gdef"},"TealType":{".class":"SymbolTableNode","cross_ref":"pyteal.types.TealType","kind":"Gdef"},"__annotations__":{".class":"SymbolTableNode","kind":"Gdef","node":{".class":"Var","flags":["is_ready"],"fullname":"pyteal.ast.assert_.__annotations__","name":"__annotations__","type":{".class":"Instance","args":["builtins.str",{".class":"AnyType","missing_import_name":null,"source_any":null,"type_of_any":6}],"type_ref":"builtins.dict"}}},"__doc__":{".class":"SymbolTableNode","kind":"Gdef","node":{".class":"Var","flags":["is_ready"],"fullname":"pyteal.ast.assert_.__doc__","name":"__doc__","type":"builtins.str"}},"__file__":{".class":"SymbolTableNode","kind":"Gdef","node":{".class":"Var","flags":["is_ready"],"fullname":"pyteal.ast.assert_.__file__","name":"__file__","type":"builtins.str"}},"__name__":{".class":"SymbolTableNode","kind":"Gdef","node":{".class":"Var","flags":["is_ready"],"fullname":"pyteal.ast.assert_.__name__","name":"__name__","type":"builtins.str"}},"__package__":{".class":"SymbolTableNode","kind":"Gdef","node":{".class":"Var","flags":["is_ready"],"fullname":"pyteal.ast.assert_.__package__","name":"__package__","type":"builtins.str"}},"require_type":{".class":"SymbolTableNode","cross_ref":"pyteal.types.require_type","kind":"Gdef"}},"path":"c:\\Users\\HP\\anaconda3\\Lib\\site-packages\\pyteal\\ast\\assert_.py"}