{".class":"MypyFile","_fullname":"pyteal.stack_frame","future_import_flags":[],"is_partial_stub_package":false,"is_stub":false,"names":{".class":"SymbolTable","AST":{".class":"SymbolTableNode","cross_ref":"_ast.AST","kind":"Gdef"},"Callable":{".class":"SymbolTableNode","cross_ref":"typing.Callable","kind":"Gdef"},"FeatureGates":{".class":"SymbolTableNode","kind":"Gdef","node":{".class":"Var","flags":["is_suppressed_import","is_ready","is_inferred"],"fullname":"pyteal.stack_frame.FeatureGates","name":"FeatureGates","type":{".class":"AnyType","missing_import_name":"pyteal.stack_frame.FeatureGates","source_any":null,"type_of_any":3}}},"Final":{".class":"SymbolTableNode","cross_ref":"typing.Final","kind":"Gdef"},"FrameInfo":{".class":"SymbolTableNode","cross_ref":"inspect.FrameInfo","kind":"Gdef"},"FunctionDef":{".class":"SymbolTableNode","cross_ref":"_ast.FunctionDef","kind":"Gdef"},"IntEnum":{".class":"SymbolTableNode","cross_ref":"enum.IntEnum","kind":"Gdef"},"NatalStackFrame":{".class":"SymbolTableNode","kind":"Gdef","node":{".class":"TypeInfo","_promote":[],"abstract_attributes":[],"alt_promote":null,"bases":["builtins.object"],"dataclass_transform_spec":null,"declared_metaclass":null,"defn":{".class":"ClassDef","fullname":"pyteal.stack_frame.NatalStackFrame","name":"NatalStackFrame","type_vars":[]},"deletable_attributes":[],"flags":[],"fullname":"pyteal.stack_frame.NatalStackFrame","has_param_spec_type":false,"metaclass_type":null,"metadata":{},"module_name":"pyteal.stack_frame","mro":["pyteal.stack_frame.NatalStackFrame","builtins.object"],"names":{".class":"SymbolTable","__init__":{".class":"SymbolTableNode","kind":"Mdef","node":{".class":"FuncDef","abstract_status":0,"arg_kinds":[0],"arg_names":["self"],"dataclass_transform_spec":null,"flags":[],"fullname":"pyteal.stack_frame.NatalStackFrame.__init__","name":"__init__","type":null}},"__len__":{".class":"SymbolTableNode","kind":"Mdef","node":{".class":"FuncDef","abstract_status":0,"arg_kinds":[0],"arg_names":[null],"dataclass_transform_spec":null,"flags":[],"fullname":"pyteal.stack_frame.NatalStackFrame.__len__","name":"__len__","type":{".class":"CallableType","arg_kinds":[0],"arg_names":[null],"arg_types":["pyteal.stack_frame.NatalStackFrame"],"bound_args":[],"def_extras":{"first_arg":"self"},"fallback":"builtins.function","from_concatenate":false,"implicit":false,"imprecise_arg_kinds":false,"is_ellipsis_args":false,"name":"__len__ of NatalStackFrame","ret_type":"builtins.int","type_guard":null,"unpack_kwargs":false,"variables":[]}}},"__repr__":{".class":"SymbolTableNode","kind":"Mdef","node":{".class":"FuncDef","abstract_status":0,"arg_kinds":[0],"arg_names":[null],"dataclass_transform_spec":null,"flags":[],"fullname":"pyteal.stack_frame.NatalStackFrame.__repr__","name":"__repr__","type":{".class":"CallableType","arg_kinds":[0],"arg_names":[null],"arg_types":["pyteal.stack_frame.NatalStackFrame"],"bound_args":[],"def_extras":{"first_arg":"self"},"fallback":"builtins.function","from_concatenate":false,"implicit":false,"imprecise_arg_kinds":false,"is_ellipsis_args":false,"name":"__repr__ of NatalStackFrame","ret_type":"builtins.str","type_guard":null,"unpack_kwargs":false,"variables":[]}}},"_best_frame":{".class":"SymbolTableNode","kind":"Mdef","node":{".class":"FuncDef","abstract_status":0,"arg_kinds":[0],"arg_names":["self"],"dataclass_transform_spec":null,"flags":[],"fullname":"pyteal.stack_frame.NatalStackFrame._best_frame","name":"_best_frame","type":{".class":"CallableType","arg_kinds":[0],"arg_names":["self"],"arg_types":["pyteal.stack_frame.NatalStackFrame"],"bound_args":[],"def_extras":{"first_arg":"self"},"fallback":"builtins.function","from_concatenate":false,"implicit":false,"imprecise_arg_kinds":false,"is_ellipsis_args":false,"name":"_best_frame of NatalStackFrame","ret_type":"pyteal.stack_frame.StackFrame","type_guard":null,"unpack_kwargs":false,"variables":[]}}},"_best_frame_as_pyteal_frame":{".class":"SymbolTableNode","kind":"Mdef","node":{".class":"FuncDef","abstract_status":0,"arg_kinds":[0],"arg_names":["self"],"dataclass_transform_spec":null,"flags":[],"fullname":"pyteal.stack_frame.NatalStackFrame._best_frame_as_pyteal_frame","name":"_best_frame_as_pyteal_frame","type":{".class":"CallableType","arg_kinds":[0],"arg_names":["self"],"arg_types":["pyteal.stack_frame.NatalStackFrame"],"bound_args":[],"def_extras":{"first_arg":"self"},"fallback":"builtins.function","from_concatenate":false,"implicit":false,"imprecise_arg_kinds":false,"is_ellipsis_args":false,"name":"_best_frame_as_pyteal_frame of NatalStackFrame","ret_type":{".class":"UnionType","items":["pyteal.stack_frame.PyTealFrame",{".class":"NoneType"}]},"type_guard":null,"unpack_kwargs":false,"variables":[]}}},"_debug_asts":{".class":"SymbolTableNode","kind":"Mdef","node":{".class":"Decorator","func":{".class":"FuncDef","abstract_status":0,"arg_kinds":[0,2],"arg_names":["cls","exprs"],"dataclass_transform_spec":null,"flags":["is_class","is_decorated"],"fullname":"pyteal.stack_frame.NatalStackFrame._debug_asts","name":"_debug_asts","type":{".class":"CallableType","arg_kinds":[0,2],"arg_names":["cls","exprs"],"arg_types":[{".class":"TypeType","item":"pyteal.stack_frame.NatalStackFrame"},{".class":"AnyType","missing_import_name":null,"source_any":null,"type_of_any":6}],"bound_args":[],"def_extras":{"first_arg":"cls"},"fallback":"builtins.function","from_concatenate":false,"implicit":false,"imprecise_arg_kinds":false,"is_ellipsis_args":false,"name":"_debug_asts of NatalStackFrame","ret_type":{".class":"NoneType"},"type_guard":null,"unpack_kwargs":false,"variables":[]}},"is_overload":false,"var":{".class":"Var","flags":["is_initialized_in_class","is_classmethod","is_ready","is_inferred"],"fullname":"pyteal.stack_frame.NatalStackFrame._debug_asts","name":"_debug_asts","type":{".class":"CallableType","arg_kinds":[0,2],"arg_names":["cls","exprs"],"arg_types":[{".class":"TypeType","item":"pyteal.stack_frame.NatalStackFrame"},{".class":"AnyType","missing_import_name":null,"source_any":null,"type_of_any":6}],"bound_args":[],"def_extras":{"first_arg":"cls"},"fallback":"builtins.function","from_concatenate":false,"implicit":false,"imprecise_arg_kinds":false,"is_ellipsis_args":false,"name":"_debug_asts of NatalStackFrame","ret_type":{".class":"NoneType"},"type_guard":null,"unpack_kwargs":false,"variables":[]}}}},"_debugging":{".class":"SymbolTableNode","kind":"Mdef","node":{".class":"Decorator","func":{".class":"FuncDef","abstract_status":0,"arg_kinds":[],"arg_names":[],"dataclass_transform_spec":null,"flags":["is_static","is_decorated"],"fullname":"pyteal.stack_frame.NatalStackFrame._debugging","name":"_debugging","type":{".class":"CallableType","arg_kinds":[],"arg_names":[],"arg_types":[],"bound_args":[],"def_extras":{"first_arg":null},"fallback":"builtins.function","from_concatenate":false,"implicit":false,"imprecise_arg_kinds":false,"is_ellipsis_args":false,"name":"_debugging of NatalStackFrame","ret_type":"builtins.bool","type_guard":null,"unpack_kwargs":false,"variables":[]}},"is_overload":false,"var":{".class":"Var","flags":["is_initialized_in_class","is_staticmethod","is_ready","is_inferred"],"fullname":"pyteal.stack_frame.NatalStackFrame._debugging","name":"_debugging","type":{".class":"CallableType","arg_kinds":[],"arg_names":[],"arg_types":[],"bound_args":[],"def_extras":{"first_arg":null},"fallback":"builtins.function","from_concatenate":false,"implicit":false,"imprecise_arg_kinds":false,"is_ellipsis_args":false,"name":"_debugging of NatalStackFrame","ret_type":"builtins.bool","type_guard":null,"unpack_kwargs":false,"variables":[]}}}},"_frames":{".class":"SymbolTableNode","implicit":true,"kind":"Mdef","node":{".class":"Var","flags":["explicit_self_type","is_ready","is_inferred"],"fullname":"pyteal.stack_frame.NatalStackFrame._frames","name":"_frames","type":{".class":"Instance","args":["pyteal.stack_frame.StackFrame"],"type_ref":"builtins.list"}}},"_keep_all_debugging":{".class":"SymbolTableNode","kind":"Mdef","node":{".class":"Var","flags":["is_initialized_in_class","is_ready","is_inferred","has_explicit_value"],"fullname":"pyteal.stack_frame.NatalStackFrame._keep_all_debugging","name":"_keep_all_debugging","type":"builtins.bool"}},"_pyteal_gen":{".class":"SymbolTableNode","implicit":true,"kind":"Mdef","node":{".class":"Var","flags":["explicit_self_type","is_ready","is_inferred"],"fullname":"pyteal.stack_frame.NatalStackFrame._pyteal_gen","name":"_pyteal_gen","type":"builtins.bool"}},"_reframe_asts":{".class":"SymbolTableNode","kind":"Mdef","node":{".class":"Decorator","func":{".class":"FuncDef","abstract_status":0,"arg_kinds":[0,0,2],"arg_names":["cls","stack_frames","exprs"],"dataclass_transform_spec":null,"flags":["is_class","is_decorated"],"fullname":"pyteal.stack_frame.NatalStackFrame._reframe_asts","name":"_reframe_asts","type":{".class":"CallableType","arg_kinds":[0,0,2],"arg_names":["cls","stack_frames","exprs"],"arg_types":[{".class":"TypeType","item":"pyteal.stack_frame.NatalStackFrame"},"pyteal.stack_frame.NatalStackFrame",{".class":"AnyType","missing_import_name":null,"source_any":null,"type_of_any":6}],"bound_args":[],"def_extras":{"first_arg":"cls"},"fallback":"builtins.function","from_concatenate":false,"implicit":false,"imprecise_arg_kinds":false,"is_ellipsis_args":false,"name":"_reframe_asts of NatalStackFrame","ret_type":{".class":"NoneType"},"type_guard":null,"unpack_kwargs":false,"variables":[]}},"is_overload":false,"var":{".class":"Var","flags":["is_initialized_in_class","is_classmethod","is_ready","is_inferred"],"fullname":"pyteal.stack_frame.NatalStackFrame._reframe_asts","name":"_reframe_asts","type":{".class":"CallableType","arg_kinds":[0,0,2],"arg_names":["cls","stack_frames","exprs"],"arg_types":[{".class":"TypeType","item":"pyteal.stack_frame.NatalStackFrame"},"pyteal.stack_frame.NatalStackFrame",{".class":"AnyType","missing_import_name":null,"source_any":null,"type_of_any":6}],"bound_args":[],"def_extras":{"first_arg":"cls"},"fallback":"builtins.function","from_concatenate":false,"implicit":false,"imprecise_arg_kinds":false,"is_ellipsis_args":false,"name":"_reframe_asts of NatalStackFrame","ret_type":{".class":"NoneType"},"type_guard":null,"unpack_kwargs":false,"variables":[]}}}},"_walk_asts":{".class":"SymbolTableNode","kind":"Mdef","node":{".class":"Decorator","func":{".class":"FuncDef","abstract_status":0,"arg_kinds":[0,0,2,5],"arg_names":["cls","func","exprs","skipping"],"dataclass_transform_spec":null,"flags":["is_class","is_decorated"],"fullname":"pyteal.stack_frame.NatalStackFrame._walk_asts","name":"_walk_asts","type":{".class":"CallableType","arg_kinds":[0,0,2,5],"arg_names":["cls","func","exprs","skipping"],"arg_types":[{".class":"TypeType","item":"pyteal.stack_frame.NatalStackFrame"},{".class":"CallableType","arg_kinds":[0],"arg_names":[null],"arg_types":[{".class":"AnyType","missing_import_name":null,"source_any":null,"type_of_any":6}],"bound_args":[],"def_extras":{},"fallback":"builtins.function","from_concatenate":false,"implicit":false,"imprecise_arg_kinds":false,"is_ellipsis_args":false,"name":null,"ret_type":"builtins.bool","type_guard":null,"unpack_kwargs":false,"variables":[]},{".class":"AnyType","missing_import_name":null,"source_any":null,"type_of_any":6},"builtins.bool"],"bound_args":[],"def_extras":{"first_arg":"cls"},"fallback":"builtins.function","from_concatenate":false,"implicit":false,"imprecise_arg_kinds":false,"is_ellipsis_args":false,"name":"_walk_asts of NatalStackFrame","ret_type":{".class":"NoneType"},"type_guard":null,"unpack_kwargs":false,"variables":[]}},"is_overload":false,"var":{".class":"Var","flags":["is_initialized_in_class","is_classmethod","is_ready","is_inferred"],"fullname":"pyteal.stack_frame.NatalStackFrame._walk_asts","name":"_walk_asts","type":{".class":"CallableType","arg_kinds":[0,0,2,5],"arg_names":["cls","func","exprs","skipping"],"arg_types":[{".class":"TypeType","item":"pyteal.stack_frame.NatalStackFrame"},{".class":"CallableType","arg_kinds":[0],"arg_names":[null],"arg_types":[{".class":"AnyType","missing_import_name":null,"source_any":null,"type_of_any":6}],"bound_args":[],"def_extras":{},"fallback":"builtins.function","from_concatenate":false,"implicit":false,"imprecise_arg_kinds":false,"is_ellipsis_args":false,"name":null,"ret_type":"builtins.bool","type_guard":null,"unpack_kwargs":false,"variables":[]},{".class":"AnyType","missing_import_name":null,"source_any":null,"type_of_any":6},"builtins.bool"],"bound_args":[],"def_extras":{"first_arg":"cls"},"fallback":"builtins.function","from_concatenate":false,"implicit":false,"imprecise_arg_kinds":false,"is_ellipsis_args":false,"name":"_walk_asts of NatalStackFrame","ret_type":{".class":"NoneType"},"type_guard":null,"unpack_kwargs":false,"variables":[]}}}},"nodes":{".class":"SymbolTableNode","kind":"Mdef","node":{".class":"FuncDef","abstract_status":0,"arg_kinds":[0],"arg_names":["self"],"dataclass_transform_spec":null,"flags":[],"fullname":"pyteal.stack_frame.NatalStackFrame.nodes","name":"nodes","type":{".class":"CallableType","arg_kinds":[0],"arg_names":["self"],"arg_types":["pyteal.stack_frame.NatalStackFrame"],"bound_args":[],"def_extras":{"first_arg":"self"},"fallback":"builtins.function","from_concatenate":false,"implicit":false,"imprecise_arg_kinds":false,"is_ellipsis_args":false,"name":"nodes of NatalStackFrame","ret_type":{".class":"Instance","args":[{".class":"UnionType","items":["_ast.AST",{".class":"NoneType"}]}],"type_ref":"builtins.list"},"type_guard":null,"unpack_kwargs":false,"variables":[]}}},"reframe":{".class":"SymbolTableNode","kind":"Mdef","node":{".class":"FuncDef","abstract_status":0,"arg_kinds":[0,2],"arg_names":["self","exprs"],"dataclass_transform_spec":null,"flags":[],"fullname":"pyteal.stack_frame.NatalStackFrame.reframe","name":"reframe","type":{".class":"CallableType","arg_kinds":[0,2],"arg_names":["self","exprs"],"arg_types":["pyteal.stack_frame.NatalStackFrame",{".class":"AnyType","missing_import_name":null,"source_any":null,"type_of_any":6}],"bound_args":[],"def_extras":{"first_arg":"self"},"fallback":"builtins.function","from_concatenate":false,"implicit":false,"imprecise_arg_kinds":false,"is_ellipsis_args":false,"name":"reframe of NatalStackFrame","ret_type":{".class":"NoneType"},"type_guard":null,"unpack_kwargs":false,"variables":[]}}},"reframe_ops_in_blocks":{".class":"SymbolTableNode","kind":"Mdef","node":{".class":"Decorator","func":{".class":"FuncDef","abstract_status":0,"arg_kinds":[0,0,0],"arg_names":["cls","root_expr","start"],"dataclass_transform_spec":null,"flags":["is_class","is_decorated"],"fullname":"pyteal.stack_frame.NatalStackFrame.reframe_ops_in_blocks","name":"reframe_ops_in_blocks","type":{".class":"CallableType","arg_kinds":[0,0,0],"arg_names":["cls","root_expr","start"],"arg_types":[{".class":"TypeType","item":"pyteal.stack_frame.NatalStackFrame"},{".class":"AnyType","missing_import_name":null,"source_any":null,"type_of_any":6},{".class":"AnyType","missing_import_name":null,"source_any":null,"type_of_any":6}],"bound_args":[],"def_extras":{"first_arg":"cls"},"fallback":"builtins.function","from_concatenate":false,"implicit":false,"imprecise_arg_kinds":false,"is_ellipsis_args":false,"name":"reframe_ops_in_blocks of NatalStackFrame","ret_type":{".class":"NoneType"},"type_guard":null,"unpack_kwargs":false,"variables":[]}},"is_overload":false,"var":{".class":"Var","flags":["is_initialized_in_class","is_classmethod","is_ready","is_inferred"],"fullname":"pyteal.stack_frame.NatalStackFrame.reframe_ops_in_blocks","name":"reframe_ops_in_blocks","type":{".class":"CallableType","arg_kinds":[0,0,0],"arg_names":["cls","root_expr","start"],"arg_types":[{".class":"TypeType","item":"pyteal.stack_frame.NatalStackFrame"},{".class":"AnyType","missing_import_name":null,"source_any":null,"type_of_any":6},{".class":"AnyType","missing_import_name":null,"source_any":null,"type_of_any":6}],"bound_args":[],"def_extras":{"first_arg":"cls"},"fallback":"builtins.function","from_concatenate":false,"implicit":false,"imprecise_arg_kinds":false,"is_ellipsis_args":false,"name":"reframe_ops_in_blocks of NatalStackFrame","ret_type":{".class":"NoneType"},"type_guard":null,"unpack_kwargs":false,"variables":[]}}}},"sourcemapping_is_off":{".class":"SymbolTableNode","kind":"Mdef","node":{".class":"Decorator","func":{".class":"FuncDef","abstract_status":0,"arg_kinds":[],"arg_names":[],"dataclass_transform_spec":null,"flags":["is_static","is_decorated"],"fullname":"pyteal.stack_frame.NatalStackFrame.sourcemapping_is_off","name":"sourcemapping_is_off","type":{".class":"CallableType","arg_kinds":[],"arg_names":[],"arg_types":[],"bound_args":[],"def_extras":{"first_arg":null},"fallback":"builtins.function","from_concatenate":false,"implicit":false,"imprecise_arg_kinds":false,"is_ellipsis_args":false,"name":"sourcemapping_is_off of NatalStackFrame","ret_type":"builtins.bool","type_guard":null,"unpack_kwargs":false,"variables":[]}},"is_overload":false,"var":{".class":"Var","flags":["is_initialized_in_class","is_staticmethod","is_ready","is_inferred"],"fullname":"pyteal.stack_frame.NatalStackFrame.sourcemapping_is_off","name":"sourcemapping_is_off","type":{".class":"CallableType","arg_kinds":[],"arg_names":[],"arg_types":[],"bound_args":[],"def_extras":{"first_arg":null},"fallback":"builtins.function","from_concatenate":false,"implicit":false,"imprecise_arg_kinds":false,"is_ellipsis_args":false,"name":"sourcemapping_is_off of NatalStackFrame","ret_type":"builtins.bool","type_guard":null,"unpack_kwargs":false,"variables":[]}}}},"user_defined":{".class":"SymbolTableNode","kind":"Mdef","node":{".class":"FuncDef","abstract_status":0,"arg_kinds":[0],"arg_names":["self"],"dataclass_transform_spec":null,"flags":[],"fullname":"pyteal.stack_frame.NatalStackFrame.user_defined","name":"user_defined","type":{".class":"CallableType","arg_kinds":[0],"arg_names":["self"],"arg_types":["pyteal.stack_frame.NatalStackFrame"],"bound_args":[],"def_extras":{"first_arg":"self"},"fallback":"builtins.function","from_concatenate":false,"implicit":false,"imprecise_arg_kinds":false,"is_ellipsis_args":false,"name":"user_defined of NatalStackFrame","ret_type":"builtins.bool","type_guard":null,"unpack_kwargs":false,"variables":[]}}}},"self_type":{".class":"TypeVarType","default":{".class":"AnyType","missing_import_name":null,"source_any":null,"type_of_any":4},"fullname":"pyteal.stack_frame.NatalStackFrame.Self","id":0,"name":"Self","namespace":"","upper_bound":"pyteal.stack_frame.NatalStackFrame","values":[],"variance":0},"slots":null,"tuple_type":null,"type_vars":[],"typeddict_type":null}},"PT_GENERATED":{".class":"SymbolTableNode","kind":"Gdef","node":{".class":"TypeInfo","_promote":[],"abstract_attributes":[],"alt_promote":null,"bases":["builtins.object"],"dataclass_transform_spec":null,"declared_metaclass":null,"defn":{".class":"ClassDef","fullname":"pyteal.stack_frame.PT_GENERATED","name":"PT_GENERATED","type_vars":[]},"deletable_attributes":[],"flags":[],"fullname":"pyteal.stack_frame.PT_GENERATED","has_param_spec_type":false,"metaclass_type":null,"metadata":{},"module_name":"pyteal.stack_frame","mro":["pyteal.stack_frame.PT_GENERATED","builtins.object"],"names":{".class":"SymbolTable","BRANCH":{".class":"SymbolTableNode","kind":"Mdef","node":{".class":"Var","flags":["is_initialized_in_class","is_ready","is_inferred","has_explicit_value"],"fullname":"pyteal.stack_frame.PT_GENERATED.BRANCH","name":"BRANCH","type":"builtins.str"}},"BRANCH_LABEL":{".class":"SymbolTableNode","kind":"Mdef","node":{".class":"Var","flags":["is_initialized_in_class","is_ready","is_inferred","has_explicit_value"],"fullname":"pyteal.stack_frame.PT_GENERATED.BRANCH_LABEL","name":"BRANCH_LABEL","type":"builtins.str"}},"PRAGMA":{".class":"SymbolTableNode","kind":"Mdef","node":{".class":"Var","flags":["is_initialized_in_class","is_ready","is_inferred","has_explicit_value"],"fullname":"pyteal.stack_frame.PT_GENERATED.PRAGMA","name":"PRAGMA","type":"builtins.str"}},"RETURN_NONE":{".class":"SymbolTableNode","kind":"Mdef","node":{".class":"Var","flags":["is_initialized_in_class","is_ready","is_inferred","has_explicit_value"],"fullname":"pyteal.stack_frame.PT_GENERATED.RETURN_NONE","name":"RETURN_NONE","type":"builtins.str"}},"RETURN_VALUE":{".class":"SymbolTableNode","kind":"Mdef","node":{".class":"Var","flags":["is_initialized_in_class","is_ready","is_inferred","has_explicit_value"],"fullname":"pyteal.stack_frame.PT_GENERATED.RETURN_VALUE","name":"RETURN_VALUE","type":"builtins.str"}},"SUBR_LABEL":{".class":"SymbolTableNode","kind":"Mdef","node":{".class":"Var","flags":["is_initialized_in_class","is_ready","is_inferred","has_explicit_value"],"fullname":"pyteal.stack_frame.PT_GENERATED.SUBR_LABEL","name":"SUBR_LABEL","type":"builtins.str"}},"SUBR_PARAM":{".class":"SymbolTableNode","kind":"Mdef","node":{".class":"Var","flags":["is_initialized_in_class","is_ready","is_inferred","has_explicit_value"],"fullname":"pyteal.stack_frame.PT_GENERATED.SUBR_PARAM","name":"SUBR_PARAM","type":"builtins.str"}},"TYPE_ENUM_ONCOMPLETE":{".class":"SymbolTableNode","kind":"Mdef","node":{".class":"Var","flags":["is_initialized_in_class","is_ready","is_inferred","has_explicit_value"],"fullname":"pyteal.stack_frame.PT_GENERATED.TYPE_ENUM_ONCOMPLETE","name":"TYPE_ENUM_ONCOMPLETE","type":"builtins.str"}},"TYPE_ENUM_TXN":{".class":"SymbolTableNode","kind":"Mdef","node":{".class":"Var","flags":["is_initialized_in_class","is_ready","is_inferred","has_explicit_value"],"fullname":"pyteal.stack_frame.PT_GENERATED.TYPE_ENUM_TXN","name":"TYPE_ENUM_TXN","type":"builtins.str"}}},"self_type":{".class":"TypeVarType","default":{".class":"AnyType","missing_import_name":null,"source_any":null,"type_of_any":4},"fullname":"pyteal.stack_frame.PT_GENERATED.Self","id":0,"name":"Self","namespace":"","upper_bound":"pyteal.stack_frame.PT_GENERATED","values":[],"variance":0},"slots":null,"tuple_type":null,"type_vars":[],"typeddict_type":null}},"PyTealFrame":{".class":"SymbolTableNode","kind":"Gdef","node":{".class":"TypeInfo","_promote":[],"abstract_attributes":[],"alt_promote":null,"bases":["pyteal.stack_frame.StackFrame"],"dataclass_transform_spec":null,"declared_metaclass":null,"defn":{".class":"ClassDef","fullname":"pyteal.stack_frame.PyTealFrame","name":"PyTealFrame","type_vars":[]},"deletable_attributes":[],"flags":[],"fullname":"pyteal.stack_frame.PyTealFrame","has_param_spec_type":false,"metaclass_type":null,"metadata":{},"module_name":"pyteal.stack_frame","mro":["pyteal.stack_frame.PyTealFrame","pyteal.stack_frame.StackFrame","builtins.object"],"names":{".class":"SymbolTable","__eq__":{".class":"SymbolTableNode","kind":"Mdef","node":{".class":"FuncDef","abstract_status":0,"arg_kinds":[0,0],"arg_names":[null,null],"dataclass_transform_spec":null,"flags":[],"fullname":"pyteal.stack_frame.PyTealFrame.__eq__","name":"__eq__","type":{".class":"CallableType","arg_kinds":[0,0],"arg_names":[null,null],"arg_types":["pyteal.stack_frame.PyTealFrame","builtins.object"],"bound_args":[],"def_extras":{"first_arg":"self"},"fallback":"builtins.function","from_concatenate":false,"implicit":false,"imprecise_arg_kinds":false,"is_ellipsis_args":false,"name":"__eq__ of PyTealFrame","ret_type":"builtins.bool","type_guard":null,"unpack_kwargs":false,"variables":[]}}},"__init__":{".class":"SymbolTableNode","kind":"Mdef","node":{".class":"FuncDef","abstract_status":0,"arg_kinds":[0,0,0,0,0,1,1],"arg_names":["self","frame_info","node","creator","full_stack","rel_paths","parent"],"dataclass_transform_spec":null,"flags":[],"fullname":"pyteal.stack_frame.PyTealFrame.__init__","name":"__init__","type":{".class":"CallableType","arg_kinds":[0,0,0,0,0,1,1],"arg_names":["self","frame_info","node","creator","full_stack","rel_paths","parent"],"arg_types":["pyteal.stack_frame.PyTealFrame",{".class":"TypeAliasType","args":[],"type_ref":"inspect.FrameInfo"},{".class":"UnionType","items":["_ast.AST",{".class":"NoneType"}]},"pyteal.stack_frame.NatalStackFrame",{".class":"UnionType","items":[{".class":"Instance","args":[{".class":"TypeAliasType","args":[],"type_ref":"inspect.FrameInfo"}],"type_ref":"builtins.list"},{".class":"NoneType"}]},"builtins.bool",{".class":"UnionType","items":["pyteal.stack_frame.PyTealFrame",{".class":"NoneType"}]}],"bound_args":[],"def_extras":{"first_arg":"self"},"fallback":"builtins.function","from_concatenate":false,"implicit":false,"imprecise_arg_kinds":false,"is_ellipsis_args":false,"name":"__init__ of PyTealFrame","ret_type":{".class":"NoneType"},"type_guard":null,"unpack_kwargs":false,"variables":[]}}},"__repr__":{".class":"SymbolTableNode","kind":"Mdef","node":{".class":"FuncDef","abstract_status":0,"arg_kinds":[0],"arg_names":[null],"dataclass_transform_spec":null,"flags":[],"fullname":"pyteal.stack_frame.PyTealFrame.__repr__","name":"__repr__","type":{".class":"CallableType","arg_kinds":[0],"arg_names":[null],"arg_types":["pyteal.stack_frame.PyTealFrame"],"bound_args":[],"def_extras":{"first_arg":"self"},"fallback":"builtins.function","from_concatenate":false,"implicit":false,"imprecise_arg_kinds":false,"is_ellipsis_args":false,"name":"__repr__ of PyTealFrame","ret_type":"builtins.str","type_guard":null,"unpack_kwargs":false,"variables":[]}}},"__str__":{".class":"SymbolTableNode","kind":"Mdef","node":{".class":"FuncDef","abstract_status":0,"arg_kinds":[0],"arg_names":[null],"dataclass_transform_spec":null,"flags":[],"fullname":"pyteal.stack_frame.PyTealFrame.__str__","name":"__str__","type":{".class":"CallableType","arg_kinds":[0],"arg_names":[null],"arg_types":["pyteal.stack_frame.PyTealFrame"],"bound_args":[],"def_extras":{"first_arg":"self"},"fallback":"builtins.function","from_concatenate":false,"implicit":false,"imprecise_arg_kinds":false,"is_ellipsis_args":false,"name":"__str__ of PyTealFrame","ret_type":"builtins.str","type_guard":null,"unpack_kwargs":false,"variables":[]}}},"_file":{".class":"SymbolTableNode","implicit":true,"kind":"Mdef","node":{".class":"Var","flags":["explicit_self_type","is_ready","is_inferred"],"fullname":"pyteal.stack_frame.PyTealFrame._file","name":"_file","type":{".class":"UnionType","items":["builtins.str",{".class":"NoneType"}]}}},"_hybrid_impl":{".class":"SymbolTableNode","kind":"Mdef","node":{".class":"Decorator","func":{".class":"FuncDef","abstract_status":0,"arg_kinds":[0,0,0,0],"arg_names":["cls","code","node","pt_chunk"],"dataclass_transform_spec":null,"flags":["is_class","is_decorated"],"fullname":"pyteal.stack_frame.PyTealFrame._hybrid_impl","name":"_hybrid_impl","type":{".class":"CallableType","arg_kinds":[0,0,0,0],"arg_names":["cls","code","node","pt_chunk"],"arg_types":[{".class":"TypeType","item":"pyteal.stack_frame.PyTealFrame"},"builtins.str",{".class":"UnionType","items":["_ast.AST",{".class":"NoneType"}]},"builtins.str"],"bound_args":[],"def_extras":{"first_arg":"cls"},"fallback":"builtins.function","from_concatenate":false,"implicit":false,"imprecise_arg_kinds":false,"is_ellipsis_args":false,"name":"_hybrid_impl of PyTealFrame","ret_type":{".class":"TupleType","implicit":false,"items":["builtins.str","builtins.int"],"partial_fallback":{".class":"Instance","args":[{".class":"AnyType","missing_import_name":null,"source_any":null,"type_of_any":6}],"type_ref":"builtins.tuple"}},"type_guard":null,"unpack_kwargs":false,"variables":[]}},"is_overload":false,"var":{".class":"Var","flags":["is_initialized_in_class","is_classmethod","is_ready","is_inferred"],"fullname":"pyteal.stack_frame.PyTealFrame._hybrid_impl","name":"_hybrid_impl","type":{".class":"CallableType","arg_kinds":[0,0,0,0],"arg_names":["cls","code","node","pt_chunk"],"arg_types":[{".class":"TypeType","item":"pyteal.stack_frame.PyTealFrame"},"builtins.str",{".class":"UnionType","items":["_ast.AST",{".class":"NoneType"}]},"builtins.str"],"bound_args":[],"def_extras":{"first_arg":"cls"},"fallback":"builtins.function","from_concatenate":false,"implicit":false,"imprecise_arg_kinds":false,"is_ellipsis_args":false,"name":"_hybrid_impl of PyTealFrame","ret_type":{".class":"TupleType","implicit":false,"items":["builtins.str","builtins.int"],"partial_fallback":{".class":"Instance","args":[{".class":"AnyType","missing_import_name":null,"source_any":null,"type_of_any":6}],"type_ref":"builtins.tuple"}},"type_guard":null,"unpack_kwargs":false,"variables":[]}}}},"_hybrid_w_offset":{".class":"SymbolTableNode","kind":"Mdef","node":{".class":"FuncDef","abstract_status":0,"arg_kinds":[0],"arg_names":["self"],"dataclass_transform_spec":null,"flags":[],"fullname":"pyteal.stack_frame.PyTealFrame._hybrid_w_offset","name":"_hybrid_w_offset","type":{".class":"CallableType","arg_kinds":[0],"arg_names":["self"],"arg_types":["pyteal.stack_frame.PyTealFrame"],"bound_args":[],"def_extras":{"first_arg":"self"},"fallback":"builtins.function","from_concatenate":false,"implicit":false,"imprecise_arg_kinds":false,"is_ellipsis_args":false,"name":"_hybrid_w_offset of PyTealFrame","ret_type":{".class":"TupleType","implicit":false,"items":["builtins.str","builtins.int"],"partial_fallback":{".class":"Instance","args":[{".class":"AnyType","missing_import_name":null,"source_any":null,"type_of_any":6}],"type_ref":"builtins.tuple"}},"type_guard":null,"unpack_kwargs":false,"variables":[]}}},"_raw_code":{".class":"SymbolTableNode","implicit":true,"kind":"Mdef","node":{".class":"Var","flags":["explicit_self_type","is_ready","is_inferred"],"fullname":"pyteal.stack_frame.PyTealFrame._raw_code","name":"_raw_code","type":{".class":"UnionType","items":["builtins.str",{".class":"NoneType"}]}}},"_root":{".class":"SymbolTableNode","implicit":true,"kind":"Mdef","node":{".class":"Var","flags":["explicit_self_type","is_ready","is_inferred"],"fullname":"pyteal.stack_frame.PyTealFrame._root","name":"_root","type":{".class":"UnionType","items":["builtins.str",{".class":"NoneType"}]}}},"_status":{".class":"SymbolTableNode","implicit":true,"kind":"Mdef","node":{".class":"Var","flags":["explicit_self_type","is_ready","is_inferred"],"fullname":"pyteal.stack_frame.PyTealFrame._status","name":"_status","type":{".class":"UnionType","items":["pyteal.stack_frame.PyTealFrameStatus",{".class":"NoneType"}]}}},"_str_impl":{".class":"SymbolTableNode","kind":"Mdef","node":{".class":"FuncDef","abstract_status":0,"arg_kinds":[0,1],"arg_names":["self","verbose"],"dataclass_transform_spec":null,"flags":[],"fullname":"pyteal.stack_frame.PyTealFrame._str_impl","name":"_str_impl","type":{".class":"CallableType","arg_kinds":[0,1],"arg_names":["self","verbose"],"arg_types":["pyteal.stack_frame.PyTealFrame","builtins.bool"],"bound_args":[],"def_extras":{"first_arg":"self"},"fallback":"builtins.function","from_concatenate":false,"implicit":false,"imprecise_arg_kinds":false,"is_ellipsis_args":false,"name":"_str_impl of PyTealFrame","ret_type":"builtins.str","type_guard":null,"unpack_kwargs":false,"variables":[]}}},"clone":{".class":"SymbolTableNode","kind":"Mdef","node":{".class":"FuncDef","abstract_status":0,"arg_kinds":[0,0],"arg_names":["self","status"],"dataclass_transform_spec":null,"flags":[],"fullname":"pyteal.stack_frame.PyTealFrame.clone","name":"clone","type":{".class":"CallableType","arg_kinds":[0,0],"arg_names":["self","status"],"arg_types":["pyteal.stack_frame.PyTealFrame","pyteal.stack_frame.PyTealFrameStatus"],"bound_args":[],"def_extras":{"first_arg":"self"},"fallback":"builtins.function","from_concatenate":false,"implicit":false,"imprecise_arg_kinds":false,"is_ellipsis_args":false,"name":"clone of PyTealFrame","ret_type":"pyteal.stack_frame.PyTealFrame","type_guard":null,"unpack_kwargs":false,"variables":[]}}},"code_qualname":{".class":"SymbolTableNode","kind":"Mdef","node":{".class":"FuncDef","abstract_status":0,"arg_kinds":[0],"arg_names":["self"],"dataclass_transform_spec":null,"flags":[],"fullname":"pyteal.stack_frame.PyTealFrame.code_qualname","name":"code_qualname","type":{".class":"CallableType","arg_kinds":[0],"arg_names":["self"],"arg_types":["pyteal.stack_frame.PyTealFrame"],"bound_args":[],"def_extras":{"first_arg":"self"},"fallback":"builtins.function","from_concatenate":false,"implicit":false,"imprecise_arg_kinds":false,"is_ellipsis_args":false,"name":"code_qualname of PyTealFrame","ret_type":"builtins.str","type_guard":null,"unpack_kwargs":false,"variables":[]}}},"column":{".class":"SymbolTableNode","kind":"Mdef","node":{".class":"FuncDef","abstract_status":0,"arg_kinds":[0],"arg_names":["self"],"dataclass_transform_spec":null,"flags":[],"fullname":"pyteal.stack_frame.PyTealFrame.column","name":"column","type":{".class":"CallableType","arg_kinds":[0],"arg_names":["self"],"arg_types":["pyteal.stack_frame.PyTealFrame"],"bound_args":[],"def_extras":{"first_arg":"self"},"fallback":"builtins.function","from_concatenate":false,"implicit":false,"imprecise_arg_kinds":false,"is_ellipsis_args":false,"name":"column of PyTealFrame","ret_type":"builtins.int","type_guard":null,"unpack_kwargs":false,"variables":[]}}},"compiler_generated_reason":{".class":"SymbolTableNode","kind":"Mdef","node":{".class":"FuncDef","abstract_status":0,"arg_kinds":[0],"arg_names":["self"],"dataclass_transform_spec":null,"flags":[],"fullname":"pyteal.stack_frame.PyTealFrame.compiler_generated_reason","name":"compiler_generated_reason","type":{".class":"CallableType","arg_kinds":[0],"arg_names":["self"],"arg_types":["pyteal.stack_frame.PyTealFrame"],"bound_args":[],"def_extras":{"first_arg":"self"},"fallback":"builtins.function","from_concatenate":false,"implicit":false,"imprecise_arg_kinds":false,"is_ellipsis_args":false,"name":"compiler_generated_reason of PyTealFrame","ret_type":{".class":"UnionType","items":["builtins.str",{".class":"NoneType"}]},"type_guard":null,"unpack_kwargs":false,"variables":[]}}},"failed_ast":{".class":"SymbolTableNode","kind":"Mdef","node":{".class":"FuncDef","abstract_status":0,"arg_kinds":[0],"arg_names":["self"],"dataclass_transform_spec":null,"flags":[],"fullname":"pyteal.stack_frame.PyTealFrame.failed_ast","name":"failed_ast","type":{".class":"CallableType","arg_kinds":[0],"arg_names":["self"],"arg_types":["pyteal.stack_frame.PyTealFrame"],"bound_args":[],"def_extras":{"first_arg":"self"},"fallback":"builtins.function","from_concatenate":false,"implicit":false,"imprecise_arg_kinds":false,"is_ellipsis_args":false,"name":"failed_ast of PyTealFrame","ret_type":"builtins.bool","type_guard":null,"unpack_kwargs":false,"variables":[]}}},"file":{".class":"SymbolTableNode","kind":"Mdef","node":{".class":"FuncDef","abstract_status":0,"arg_kinds":[0],"arg_names":["self"],"dataclass_transform_spec":null,"flags":[],"fullname":"pyteal.stack_frame.PyTealFrame.file","name":"file","type":{".class":"CallableType","arg_kinds":[0],"arg_names":["self"],"arg_types":["pyteal.stack_frame.PyTealFrame"],"bound_args":[],"def_extras":{"first_arg":"self"},"fallback":"builtins.function","from_concatenate":false,"implicit":false,"imprecise_arg_kinds":false,"is_ellipsis_args":false,"name":"file of PyTealFrame","ret_type":"builtins.str","type_guard":null,"unpack_kwargs":false,"variables":[]}}},"hybrid_unparsed":{".class":"SymbolTableNode","kind":"Mdef","node":{".class":"FuncDef","abstract_status":0,"arg_kinds":[0],"arg_names":["self"],"dataclass_transform_spec":null,"flags":[],"fullname":"pyteal.stack_frame.PyTealFrame.hybrid_unparsed","name":"hybrid_unparsed","type":{".class":"CallableType","arg_kinds":[0],"arg_names":["self"],"arg_types":["pyteal.stack_frame.PyTealFrame"],"bound_args":[],"def_extras":{"first_arg":"self"},"fallback":"builtins.function","from_concatenate":false,"implicit":false,"imprecise_arg_kinds":false,"is_ellipsis_args":false,"name":"hybrid_unparsed of PyTealFrame","ret_type":"builtins.str","type_guard":null,"unpack_kwargs":false,"variables":[]}}},"lineno":{".class":"SymbolTableNode","kind":"Mdef","node":{".class":"FuncDef","abstract_status":0,"arg_kinds":[0],"arg_names":["self"],"dataclass_transform_spec":null,"flags":[],"fullname":"pyteal.stack_frame.PyTealFrame.lineno","name":"lineno","type":{".class":"CallableType","arg_kinds":[0],"arg_names":["self"],"arg_types":["pyteal.stack_frame.PyTealFrame"],"bound_args":[],"def_extras":{"first_arg":"self"},"fallback":"builtins.function","from_concatenate":false,"implicit":false,"imprecise_arg_kinds":false,"is_ellipsis_args":false,"name":"lineno of PyTealFrame","ret_type":{".class":"UnionType","items":["builtins.int",{".class":"NoneType"}]},"type_guard":null,"unpack_kwargs":false,"variables":[]}}},"location":{".class":"SymbolTableNode","kind":"Mdef","node":{".class":"FuncDef","abstract_status":0,"arg_kinds":[0],"arg_names":["self"],"dataclass_transform_spec":null,"flags":[],"fullname":"pyteal.stack_frame.PyTealFrame.location","name":"location","type":{".class":"CallableType","arg_kinds":[0],"arg_names":["self"],"arg_types":["pyteal.stack_frame.PyTealFrame"],"bound_args":[],"def_extras":{"first_arg":"self"},"fallback":"builtins.function","from_concatenate":false,"implicit":false,"imprecise_arg_kinds":false,"is_ellipsis_args":false,"name":"location of PyTealFrame","ret_type":"builtins.str","type_guard":null,"unpack_kwargs":false,"variables":[]}}},"node_col_offset":{".class":"SymbolTableNode","kind":"Mdef","node":{".class":"FuncDef","abstract_status":0,"arg_kinds":[0],"arg_names":["self"],"dataclass_transform_spec":null,"flags":[],"fullname":"pyteal.stack_frame.PyTealFrame.node_col_offset","name":"node_col_offset","type":{".class":"CallableType","arg_kinds":[0],"arg_names":["self"],"arg_types":["pyteal.stack_frame.PyTealFrame"],"bound_args":[],"def_extras":{"first_arg":"self"},"fallback":"builtins.function","from_concatenate":false,"implicit":false,"imprecise_arg_kinds":false,"is_ellipsis_args":false,"name":"node_col_offset of PyTealFrame","ret_type":{".class":"UnionType","items":["builtins.int",{".class":"NoneType"}]},"type_guard":null,"unpack_kwargs":false,"variables":[]}}},"node_end_col_offset":{".class":"SymbolTableNode","kind":"Mdef","node":{".class":"FuncDef","abstract_status":0,"arg_kinds":[0],"arg_names":["self"],"dataclass_transform_spec":null,"flags":[],"fullname":"pyteal.stack_frame.PyTealFrame.node_end_col_offset","name":"node_end_col_offset","type":{".class":"CallableType","arg_kinds":[0],"arg_names":["self"],"arg_types":["pyteal.stack_frame.PyTealFrame"],"bound_args":[],"def_extras":{"first_arg":"self"},"fallback":"builtins.function","from_concatenate":false,"implicit":false,"imprecise_arg_kinds":false,"is_ellipsis_args":false,"name":"node_end_col_offset of PyTealFrame","ret_type":{".class":"UnionType","items":["builtins.int",{".class":"NoneType"}]},"type_guard":null,"unpack_kwargs":false,"variables":[]}}},"node_end_lineno":{".class":"SymbolTableNode","kind":"Mdef","node":{".class":"FuncDef","abstract_status":0,"arg_kinds":[0],"arg_names":["self"],"dataclass_transform_spec":null,"flags":[],"fullname":"pyteal.stack_frame.PyTealFrame.node_end_lineno","name":"node_end_lineno","type":{".class":"CallableType","arg_kinds":[0],"arg_names":["self"],"arg_types":["pyteal.stack_frame.PyTealFrame"],"bound_args":[],"def_extras":{"first_arg":"self"},"fallback":"builtins.function","from_concatenate":false,"implicit":false,"imprecise_arg_kinds":false,"is_ellipsis_args":false,"name":"node_end_lineno of PyTealFrame","ret_type":{".class":"UnionType","items":["builtins.int",{".class":"NoneType"}]},"type_guard":null,"unpack_kwargs":false,"variables":[]}}},"node_lineno":{".class":"SymbolTableNode","kind":"Mdef","node":{".class":"FuncDef","abstract_status":0,"arg_kinds":[0],"arg_names":["self"],"dataclass_transform_spec":null,"flags":[],"fullname":"pyteal.stack_frame.PyTealFrame.node_lineno","name":"node_lineno","type":{".class":"CallableType","arg_kinds":[0],"arg_names":["self"],"arg_types":["pyteal.stack_frame.PyTealFrame"],"bound_args":[],"def_extras":{"first_arg":"self"},"fallback":"builtins.function","from_concatenate":false,"implicit":false,"imprecise_arg_kinds":false,"is_ellipsis_args":false,"name":"node_lineno of PyTealFrame","ret_type":{".class":"UnionType","items":["builtins.int",{".class":"NoneType"}]},"type_guard":null,"unpack_kwargs":false,"variables":[]}}},"node_source":{".class":"SymbolTableNode","kind":"Mdef","node":{".class":"FuncDef","abstract_status":0,"arg_kinds":[0],"arg_names":["self"],"dataclass_transform_spec":null,"flags":[],"fullname":"pyteal.stack_frame.PyTealFrame.node_source","name":"node_source","type":{".class":"CallableType","arg_kinds":[0],"arg_names":["self"],"arg_types":["pyteal.stack_frame.PyTealFrame"],"bound_args":[],"def_extras":{"first_arg":"self"},"fallback":"builtins.function","from_concatenate":false,"implicit":false,"imprecise_arg_kinds":false,"is_ellipsis_args":false,"name":"node_source of PyTealFrame","ret_type":"builtins.str","type_guard":null,"unpack_kwargs":false,"variables":[]}}},"node_source_window":{".class":"SymbolTableNode","kind":"Mdef","node":{".class":"FuncDef","abstract_status":0,"arg_kinds":[0],"arg_names":["self"],"dataclass_transform_spec":null,"flags":[],"fullname":"pyteal.stack_frame.PyTealFrame.node_source_window","name":"node_source_window","type":{".class":"CallableType","arg_kinds":[0],"arg_names":["self"],"arg_types":["pyteal.stack_frame.PyTealFrame"],"bound_args":[],"def_extras":{"first_arg":"self"},"fallback":"builtins.function","from_concatenate":false,"implicit":false,"imprecise_arg_kinds":false,"is_ellipsis_args":false,"name":"node_source_window of PyTealFrame","ret_type":"builtins.str","type_guard":null,"unpack_kwargs":false,"variables":[]}}},"parent":{".class":"SymbolTableNode","implicit":true,"kind":"Mdef","node":{".class":"Var","flags":["is_final","explicit_self_type","is_ready","is_inferred"],"fullname":"pyteal.stack_frame.PyTealFrame.parent","name":"parent","type":{".class":"UnionType","items":["pyteal.stack_frame.PyTealFrame",{".class":"NoneType"}]}}},"raw_code":{".class":"SymbolTableNode","kind":"Mdef","node":{".class":"FuncDef","abstract_status":0,"arg_kinds":[0],"arg_names":["self"],"dataclass_transform_spec":null,"flags":[],"fullname":"pyteal.stack_frame.PyTealFrame.raw_code","name":"raw_code","type":{".class":"CallableType","arg_kinds":[0],"arg_names":["self"],"arg_types":["pyteal.stack_frame.PyTealFrame"],"bound_args":[],"def_extras":{"first_arg":"self"},"fallback":"builtins.function","from_concatenate":false,"implicit":false,"imprecise_arg_kinds":false,"is_ellipsis_args":false,"name":"raw_code of PyTealFrame","ret_type":"builtins.str","type_guard":null,"unpack_kwargs":false,"variables":[]}}},"rel_paths":{".class":"SymbolTableNode","implicit":true,"kind":"Mdef","node":{".class":"Var","flags":["is_final","explicit_self_type","is_ready","is_inferred"],"fullname":"pyteal.stack_frame.PyTealFrame.rel_paths","name":"rel_paths","type":"builtins.bool"}},"root":{".class":"SymbolTableNode","kind":"Mdef","node":{".class":"FuncDef","abstract_status":0,"arg_kinds":[0],"arg_names":["self"],"dataclass_transform_spec":null,"flags":[],"fullname":"pyteal.stack_frame.PyTealFrame.root","name":"root","type":{".class":"CallableType","arg_kinds":[0],"arg_names":["self"],"arg_types":["pyteal.stack_frame.PyTealFrame"],"bound_args":[],"def_extras":{"first_arg":"self"},"fallback":"builtins.function","from_concatenate":false,"implicit":false,"imprecise_arg_kinds":false,"is_ellipsis_args":false,"name":"root of PyTealFrame","ret_type":"builtins.str","type_guard":null,"unpack_kwargs":false,"variables":[]}}},"status":{".class":"SymbolTableNode","kind":"Mdef","node":{".class":"FuncDef","abstract_status":0,"arg_kinds":[0],"arg_names":["self"],"dataclass_transform_spec":null,"flags":[],"fullname":"pyteal.stack_frame.PyTealFrame.status","name":"status","type":{".class":"CallableType","arg_kinds":[0],"arg_names":["self"],"arg_types":["pyteal.stack_frame.PyTealFrame"],"bound_args":[],"def_extras":{"first_arg":"self"},"fallback":"builtins.function","from_concatenate":false,"implicit":false,"imprecise_arg_kinds":false,"is_ellipsis_args":false,"name":"status of PyTealFrame","ret_type":"builtins.str","type_guard":null,"unpack_kwargs":false,"variables":[]}}},"status_code":{".class":"SymbolTableNode","kind":"Mdef","node":{".class":"FuncDef","abstract_status":0,"arg_kinds":[0],"arg_names":["self"],"dataclass_transform_spec":null,"flags":[],"fullname":"pyteal.stack_frame.PyTealFrame.status_code","name":"status_code","type":{".class":"CallableType","arg_kinds":[0],"arg_names":["self"],"arg_types":["pyteal.stack_frame.PyTealFrame"],"bound_args":[],"def_extras":{"first_arg":"self"},"fallback":"builtins.function","from_concatenate":false,"implicit":false,"imprecise_arg_kinds":false,"is_ellipsis_args":false,"name":"status_code of PyTealFrame","ret_type":"pyteal.stack_frame.PyTealFrameStatus","type_guard":null,"unpack_kwargs":false,"variables":[]}}}},"self_type":{".class":"TypeVarType","default":{".class":"AnyType","missing_import_name":null,"source_any":null,"type_of_any":4},"fullname":"pyteal.stack_frame.PyTealFrame.Self","id":0,"name":"Self","namespace":"","upper_bound":"pyteal.stack_frame.PyTealFrame","values":[],"variance":0},"slots":null,"tuple_type":null,"type_vars":[],"typeddict_type":null}},"PyTealFrameStatus":{".class":"SymbolTableNode","kind":"Gdef","node":{".class":"TypeInfo","_promote":[],"abstract_attributes":[],"alt_promote":null,"bases":["enum.IntEnum"],"dataclass_transform_spec":null,"declared_metaclass":null,"defn":{".class":"ClassDef","fullname":"pyteal.stack_frame.PyTealFrameStatus","name":"PyTealFrameStatus","type_vars":[]},"deletable_attributes":[],"flags":["is_enum"],"fullname":"pyteal.stack_frame.PyTealFrameStatus","has_param_spec_type":false,"metaclass_type":"enum.EnumMeta","metadata":{},"module_name":"pyteal.stack_frame","mro":["pyteal.stack_frame.PyTealFrameStatus","enum.IntEnum","builtins.int","enum.ReprEnum","enum.Enum","builtins.object"],"names":{".class":"SymbolTable","COPACETIC":{".class":"SymbolTableNode","kind":"Mdef","node":{".class":"Var","flags":["is_initialized_in_class","is_final","is_ready","is_inferred","has_explicit_value"],"fullname":"pyteal.stack_frame.PyTealFrameStatus.COPACETIC","name":"COPACETIC","type":{".class":"Instance","args":[],"last_known_value":{".class":"LiteralType","fallback":"builtins.int","value":9},"type_ref":"builtins.int"}}},"MISSING":{".class":"SymbolTableNode","kind":"Mdef","node":{".class":"Var","flags":["is_initialized_in_class","is_final","is_ready","is_inferred","has_explicit_value"],"fullname":"pyteal.stack_frame.PyTealFrameStatus.MISSING","name":"MISSING","type":{".class":"Instance","args":[],"last_known_value":{".class":"LiteralType","fallback":"builtins.int","value":0},"type_ref":"builtins.int"}}},"MISSING_AST":{".class":"SymbolTableNode","kind":"Mdef","node":{".class":"Var","flags":["is_initialized_in_class","is_final","is_ready","is_inferred","has_explicit_value"],"fullname":"pyteal.stack_frame.PyTealFrameStatus.MISSING_AST","name":"MISSING_AST","type":{".class":"Instance","args":[],"last_known_value":{".class":"LiteralType","fallback":"builtins.int","value":1},"type_ref":"builtins.int"}}},"MISSING_CODE":{".class":"SymbolTableNode","kind":"Mdef","node":{".class":"Var","flags":["is_initialized_in_class","is_final","is_ready","is_inferred","has_explicit_value"],"fullname":"pyteal.stack_frame.PyTealFrameStatus.MISSING_CODE","name":"MISSING_CODE","type":{".class":"Instance","args":[],"last_known_value":{".class":"LiteralType","fallback":"builtins.int","value":2},"type_ref":"builtins.int"}}},"PATCHED_BY_NEXT":{".class":"SymbolTableNode","kind":"Mdef","node":{".class":"Var","flags":["is_initialized_in_class","is_final","is_ready","is_inferred","has_explicit_value"],"fullname":"pyteal.stack_frame.PyTealFrameStatus.PATCHED_BY_NEXT","name":"PATCHED_BY_NEXT","type":{".class":"Instance","args":[],"last_known_value":{".class":"LiteralType","fallback":"builtins.int","value":7},"type_ref":"builtins.int"}}},"PATCHED_BY_NEXT_OVERRIDE_PREV":{".class":"SymbolTableNode","kind":"Mdef","node":{".class":"Var","flags":["is_initialized_in_class","is_final","is_ready","is_inferred","has_explicit_value"],"fullname":"pyteal.stack_frame.PyTealFrameStatus.PATCHED_BY_NEXT_OVERRIDE_PREV","name":"PATCHED_BY_NEXT_OVERRIDE_PREV","type":{".class":"Instance","args":[],"last_known_value":{".class":"LiteralType","fallback":"builtins.int","value":5},"type_ref":"builtins.int"}}},"PATCHED_BY_PREV":{".class":"SymbolTableNode","kind":"Mdef","node":{".class":"Var","flags":["is_initialized_in_class","is_final","is_ready","is_inferred","has_explicit_value"],"fullname":"pyteal.stack_frame.PyTealFrameStatus.PATCHED_BY_PREV","name":"PATCHED_BY_PREV","type":{".class":"Instance","args":[],"last_known_value":{".class":"LiteralType","fallback":"builtins.int","value":6},"type_ref":"builtins.int"}}},"PATCHED_BY_PREV_AND_NEXT":{".class":"SymbolTableNode","kind":"Mdef","node":{".class":"Var","flags":["is_initialized_in_class","is_final","is_ready","is_inferred","has_explicit_value"],"fullname":"pyteal.stack_frame.PyTealFrameStatus.PATCHED_BY_PREV_AND_NEXT","name":"PATCHED_BY_PREV_AND_NEXT","type":{".class":"Instance","args":[],"last_known_value":{".class":"LiteralType","fallback":"builtins.int","value":8},"type_ref":"builtins.int"}}},"PATCHED_BY_PREV_OVERRIDE_NEXT":{".class":"SymbolTableNode","kind":"Mdef","node":{".class":"Var","flags":["is_initialized_in_class","is_final","is_ready","is_inferred","has_explicit_value"],"fullname":"pyteal.stack_frame.PyTealFrameStatus.PATCHED_BY_PREV_OVERRIDE_NEXT","name":"PATCHED_BY_PREV_OVERRIDE_NEXT","type":{".class":"Instance","args":[],"last_known_value":{".class":"LiteralType","fallback":"builtins.int","value":4},"type_ref":"builtins.int"}}},"PYTEAL_GENERATED":{".class":"SymbolTableNode","kind":"Mdef","node":{".class":"Var","flags":["is_initialized_in_class","is_final","is_ready","is_inferred","has_explicit_value"],"fullname":"pyteal.stack_frame.PyTealFrameStatus.PYTEAL_GENERATED","name":"PYTEAL_GENERATED","type":{".class":"Instance","args":[],"last_known_value":{".class":"LiteralType","fallback":"builtins.int","value":3},"type_ref":"builtins.int"}}},"human":{".class":"SymbolTableNode","kind":"Mdef","node":{".class":"FuncDef","abstract_status":0,"arg_kinds":[0],"arg_names":["self"],"dataclass_transform_spec":null,"flags":[],"fullname":"pyteal.stack_frame.PyTealFrameStatus.human","name":"human","type":{".class":"CallableType","arg_kinds":[0],"arg_names":["self"],"arg_types":["pyteal.stack_frame.PyTealFrameStatus"],"bound_args":[],"def_extras":{"first_arg":"self"},"fallback":"builtins.function","from_concatenate":false,"implicit":false,"imprecise_arg_kinds":false,"is_ellipsis_args":false,"name":"human of PyTealFrameStatus","ret_type":"builtins.str","type_guard":null,"unpack_kwargs":false,"variables":[]}}}},"self_type":{".class":"TypeVarType","default":{".class":"AnyType","missing_import_name":null,"source_any":null,"type_of_any":4},"fullname":"pyteal.stack_frame.PyTealFrameStatus.Self","id":0,"name":"Self","namespace":"","upper_bound":"pyteal.stack_frame.PyTealFrameStatus","values":[],"variance":0},"slots":null,"tuple_type":null,"type_vars":[],"typeddict_type":null}},"Source":{".class":"SymbolTableNode","cross_ref":"executing.executing.Source","kind":"Gdef"},"SourceMapStackFramesError":{".class":"SymbolTableNode","kind":"Gdef","node":{".class":"TypeInfo","_promote":[],"abstract_attributes":[],"alt_promote":null,"bases":["builtins.RuntimeError"],"dataclass_transform_spec":null,"declared_metaclass":null,"defn":{".class":"ClassDef","fullname":"pyteal.stack_frame.SourceMapStackFramesError","name":"SourceMapStackFramesError","type_vars":[]},"deletable_attributes":[],"flags":[],"fullname":"pyteal.stack_frame.SourceMapStackFramesError","has_param_spec_type":false,"metaclass_type":null,"metadata":{},"module_name":"pyteal.stack_frame","mro":["pyteal.stack_frame.SourceMapStackFramesError","builtins.RuntimeError","builtins.Exception","builtins.BaseException","builtins.object"],"names":{".class":"SymbolTable","__init__":{".class":"SymbolTableNode","kind":"Mdef","node":{".class":"FuncDef","abstract_status":0,"arg_kinds":[0,0],"arg_names":["self","msg"],"dataclass_transform_spec":null,"flags":[],"fullname":"pyteal.stack_frame.SourceMapStackFramesError.__init__","name":"__init__","type":{".class":"CallableType","arg_kinds":[0,0],"arg_names":["self","msg"],"arg_types":["pyteal.stack_frame.SourceMapStackFramesError","builtins.str"],"bound_args":[],"def_extras":{"first_arg":"self"},"fallback":"builtins.function","from_concatenate":false,"implicit":false,"imprecise_arg_kinds":false,"is_ellipsis_args":false,"name":"__init__ of SourceMapStackFramesError","ret_type":{".class":"NoneType"},"type_guard":null,"unpack_kwargs":false,"variables":[]}}},"__str__":{".class":"SymbolTableNode","kind":"Mdef","node":{".class":"FuncDef","abstract_status":0,"arg_kinds":[0],"arg_names":[null],"dataclass_transform_spec":null,"flags":[],"fullname":"pyteal.stack_frame.SourceMapStackFramesError.__str__","name":"__str__","type":null}},"msg":{".class":"SymbolTableNode","implicit":true,"kind":"Mdef","node":{".class":"Var","flags":["is_inferred"],"fullname":"pyteal.stack_frame.SourceMapStackFramesError.msg","name":"msg","type":"builtins.str"}}},"self_type":{".class":"TypeVarType","default":{".class":"AnyType","missing_import_name":null,"source_any":null,"type_of_any":4},"fullname":"pyteal.stack_frame.SourceMapStackFramesError.Self","id":0,"name":"Self","namespace":"","upper_bound":"pyteal.stack_frame.SourceMapStackFramesError","values":[],"variance":0},"slots":null,"tuple_type":null,"type_vars":[],"typeddict_type":null}},"StackFrame":{".class":"SymbolTableNode","kind":"Gdef","node":{".class":"TypeInfo","_promote":[],"abstract_attributes":[],"alt_promote":null,"bases":["builtins.object"],"dataclass_transform_spec":null,"declared_metaclass":null,"defn":{".class":"ClassDef","fullname":"pyteal.stack_frame.StackFrame","name":"StackFrame","type_vars":[]},"deletable_attributes":[],"flags":[],"fullname":"pyteal.stack_frame.StackFrame","has_param_spec_type":false,"metaclass_type":null,"metadata":{"dataclass":{"attributes":[{"alias":null,"column":4,"has_default":false,"is_in_init":true,"is_init_var":false,"is_neither_frozen_nor_nonfrozen":false,"kw_only":false,"line":63,"name":"frame_info","type":{".class":"TypeAliasType","args":[],"type_ref":"inspect.FrameInfo"}},{"alias":null,"column":4,"has_default":false,"is_in_init":true,"is_init_var":false,"is_neither_frozen_nor_nonfrozen":false,"kw_only":false,"line":64,"name":"node","type":{".class":"UnionType","items":["_ast.AST",{".class":"NoneType"}]}},{"alias":null,"column":4,"has_default":false,"is_in_init":true,"is_init_var":false,"is_neither_frozen_nor_nonfrozen":false,"kw_only":false,"line":65,"name":"creator","type":"pyteal.stack_frame.NatalStackFrame"},{"alias":null,"column":4,"has_default":true,"is_in_init":true,"is_init_var":false,"is_neither_frozen_nor_nonfrozen":false,"kw_only":false,"line":68,"name":"full_stack","type":{".class":"UnionType","items":[{".class":"Instance","args":[{".class":"TypeAliasType","args":[],"type_ref":"inspect.FrameInfo"}],"type_ref":"builtins.list"},{".class":"NoneType"}]}}],"frozen":true},"dataclass_tag":{}},"module_name":"pyteal.stack_frame","mro":["pyteal.stack_frame.StackFrame","builtins.object"],"names":{".class":"SymbolTable","__dataclass_fields__":{".class":"SymbolTableNode","kind":"Mdef","node":{".class":"Var","flags":["is_classvar","is_ready"],"fullname":"pyteal.stack_frame.StackFrame.__dataclass_fields__","name":"__dataclass_fields__","type":{".class":"Instance","args":["builtins.str",{".class":"Instance","args":[{".class":"AnyType","missing_import_name":null,"source_any":null,"type_of_any":2}],"type_ref":"dataclasses.Field"}],"type_ref":"builtins.dict"}},"plugin_generated":true},"__init__":{".class":"SymbolTableNode","kind":"Mdef","node":{".class":"FuncDef","abstract_status":0,"arg_kinds":[0,0,0,0,1],"arg_names":["self","frame_info","node","creator","full_stack"],"dataclass_transform_spec":null,"flags":[],"fullname":"pyteal.stack_frame.StackFrame.__init__","name":"__init__","type":{".class":"CallableType","arg_kinds":[0,0,0,0,1],"arg_names":["self","frame_info","node","creator","full_stack"],"arg_types":["pyteal.stack_frame.StackFrame",{".class":"TypeAliasType","args":[],"type_ref":"inspect.FrameInfo"},{".class":"UnionType","items":["_ast.AST",{".class":"NoneType"}]},"pyteal.stack_frame.NatalStackFrame",{".class":"UnionType","items":[{".class":"Instance","args":[{".class":"TypeAliasType","args":[],"type_ref":"inspect.FrameInfo"}],"type_ref":"builtins.list"},{".class":"NoneType"}]}],"bound_args":[],"def_extras":{},"fallback":"builtins.function","from_concatenate":false,"implicit":false,"imprecise_arg_kinds":false,"is_ellipsis_args":false,"name":"__init__ of StackFrame","ret_type":{".class":"NoneType"},"type_guard":null,"unpack_kwargs":false,"variables":[]}},"plugin_generated":true},"__match_args__":{".class":"SymbolTableNode","kind":"Mdef","node":{".class":"Var","flags":["is_ready","allow_incompatible_override"],"fullname":"pyteal.stack_frame.StackFrame.__match_args__","name":"__match_args__","type":{".class":"TupleType","implicit":false,"items":[{".class":"LiteralType","fallback":"builtins.str","value":"frame_info"},{".class":"LiteralType","fallback":"builtins.str","value":"node"},{".class":"LiteralType","fallback":"builtins.str","value":"creator"},{".class":"LiteralType","fallback":"builtins.str","value":"full_stack"}],"partial_fallback":{".class":"Instance","args":[{".class":"AnyType","missing_import_name":null,"source_any":null,"type_of_any":6}],"type_ref":"builtins.tuple"}}},"plugin_generated":true},"__mypy-replace":{".class":"SymbolTableNode","kind":"Mdef","node":{".class":"Decorator","func":{".class":"FuncDef","abstract_status":0,"arg_kinds":[5,5,5,5],"arg_names":["frame_info","node","creator","full_stack"],"dataclass_transform_spec":null,"flags":["is_static","is_decorated"],"fullname":"pyteal.stack_frame.StackFrame.__mypy-replace","name":"__mypy-replace","type":{".class":"CallableType","arg_kinds":[5,5,5,5],"arg_names":["frame_info","node","creator","full_stack"],"arg_types":[{".class":"TypeAliasType","args":[],"type_ref":"inspect.FrameInfo"},{".class":"UnionType","items":["_ast.AST",{".class":"NoneType"}]},"pyteal.stack_frame.NatalStackFrame",{".class":"UnionType","items":[{".class":"Instance","args":[{".class":"TypeAliasType","args":[],"type_ref":"inspect.FrameInfo"}],"type_ref":"builtins.list"},{".class":"NoneType"}]}],"bound_args":[],"def_extras":{},"fallback":"builtins.function","from_concatenate":false,"implicit":false,"imprecise_arg_kinds":false,"is_ellipsis_args":false,"name":"__mypy-replace of StackFrame","ret_type":{".class":"NoneType"},"type_guard":null,"unpack_kwargs":false,"variables":[]}},"is_overload":false,"var":{".class":"Var","flags":["is_staticmethod","is_ready"],"fullname":"pyteal.stack_frame.StackFrame.__mypy-replace","name":"__mypy-replace","type":{".class":"CallableType","arg_kinds":[5,5,5,5],"arg_names":["frame_info","node","creator","full_stack"],"arg_types":[{".class":"TypeAliasType","args":[],"type_ref":"inspect.FrameInfo"},{".class":"UnionType","items":["_ast.AST",{".class":"NoneType"}]},"pyteal.stack_frame.NatalStackFrame",{".class":"UnionType","items":[{".class":"Instance","args":[{".class":"TypeAliasType","args":[],"type_ref":"inspect.FrameInfo"}],"type_ref":"builtins.list"},{".class":"NoneType"}]}],"bound_args":[],"def_extras":{},"fallback":"builtins.function","from_concatenate":false,"implicit":false,"imprecise_arg_kinds":false,"is_ellipsis_args":false,"name":"__mypy-replace of StackFrame","ret_type":{".class":"NoneType"},"type_guard":null,"unpack_kwargs":false,"variables":[]}}},"plugin_generated":true},"__repr__":{".class":"SymbolTableNode","kind":"Mdef","node":{".class":"FuncDef","abstract_status":0,"arg_kinds":[0],"arg_names":[null],"dataclass_transform_spec":null,"flags":[],"fullname":"pyteal.stack_frame.StackFrame.__repr__","name":"__repr__","type":{".class":"CallableType","arg_kinds":[0],"arg_names":[null],"arg_types":["pyteal.stack_frame.StackFrame"],"bound_args":[],"def_extras":{"first_arg":"self"},"fallback":"builtins.function","from_concatenate":false,"implicit":false,"imprecise_arg_kinds":false,"is_ellipsis_args":false,"name":"__repr__ of StackFrame","ret_type":"builtins.str","type_guard":null,"unpack_kwargs":false,"variables":[]}}},"_compilation_gateways":{".class":"SymbolTableNode","kind":"Mdef","node":{".class":"Var","flags":["is_initialized_in_class","is_inferred","has_explicit_value"],"fullname":"pyteal.stack_frame.StackFrame._compilation_gateways","name":"_compilation_gateways","type":{".class":"Instance","args":["builtins.str","builtins.str"],"type_ref":"builtins.dict"}}},"_frame_info_compiler_generated":{".class":"SymbolTableNode","kind":"Mdef","node":{".class":"Decorator","func":{".class":"FuncDef","abstract_status":0,"arg_kinds":[0,0],"arg_names":["cls","f"],"dataclass_transform_spec":null,"flags":["is_class","is_decorated"],"fullname":"pyteal.stack_frame.StackFrame._frame_info_compiler_generated","name":"_frame_info_compiler_generated","type":{".class":"CallableType","arg_kinds":[0,0],"arg_names":["cls","f"],"arg_types":[{".class":"TypeType","item":"pyteal.stack_frame.StackFrame"},{".class":"TypeAliasType","args":[],"type_ref":"inspect.FrameInfo"}],"bound_args":[],"def_extras":{"first_arg":"cls"},"fallback":"builtins.function","from_concatenate":false,"implicit":false,"imprecise_arg_kinds":false,"is_ellipsis_args":false,"name":"_frame_info_compiler_generated of StackFrame","ret_type":{".class":"UnionType","items":["builtins.bool",{".class":"NoneType"}]},"type_guard":null,"unpack_kwargs":false,"variables":[]}},"is_overload":false,"var":{".class":"Var","flags":["is_initialized_in_class","is_classmethod","is_ready","is_inferred"],"fullname":"pyteal.stack_frame.StackFrame._frame_info_compiler_generated","name":"_frame_info_compiler_generated","type":{".class":"CallableType","arg_kinds":[0,0],"arg_names":["cls","f"],"arg_types":[{".class":"TypeType","item":"pyteal.stack_frame.StackFrame"},{".class":"TypeAliasType","args":[],"type_ref":"inspect.FrameInfo"}],"bound_args":[],"def_extras":{"first_arg":"cls"},"fallback":"builtins.function","from_concatenate":false,"implicit":false,"imprecise_arg_kinds":false,"is_ellipsis_args":false,"name":"_frame_info_compiler_generated of StackFrame","ret_type":{".class":"UnionType","items":["builtins.bool",{".class":"NoneType"}]},"type_guard":null,"unpack_kwargs":false,"variables":[]}}}},"_frame_info_is_pyteal":{".class":"SymbolTableNode","kind":"Mdef","node":{".class":"Decorator","func":{".class":"FuncDef","abstract_status":0,"arg_kinds":[0,0],"arg_names":["cls","f"],"dataclass_transform_spec":null,"flags":["is_class","is_decorated"],"fullname":"pyteal.stack_frame.StackFrame._frame_info_is_pyteal","name":"_frame_info_is_pyteal","type":{".class":"CallableType","arg_kinds":[0,0],"arg_names":["cls","f"],"arg_types":[{".class":"TypeType","item":"pyteal.stack_frame.StackFrame"},{".class":"TypeAliasType","args":[],"type_ref":"inspect.FrameInfo"}],"bound_args":[],"def_extras":{"first_arg":"cls"},"fallback":"builtins.function","from_concatenate":false,"implicit":false,"imprecise_arg_kinds":false,"is_ellipsis_args":false,"name":"_frame_info_is_pyteal of StackFrame","ret_type":"builtins.bool","type_guard":null,"unpack_kwargs":false,"variables":[]}},"is_overload":false,"var":{".class":"Var","flags":["is_initialized_in_class","is_classmethod","is_ready","is_inferred"],"fullname":"pyteal.stack_frame.StackFrame._frame_info_is_pyteal","name":"_frame_info_is_pyteal","type":{".class":"CallableType","arg_kinds":[0,0],"arg_names":["cls","f"],"arg_types":[{".class":"TypeType","item":"pyteal.stack_frame.StackFrame"},{".class":"TypeAliasType","args":[],"type_ref":"inspect.FrameInfo"}],"bound_args":[],"def_extras":{"first_arg":"cls"},"fallback":"builtins.function","from_concatenate":false,"implicit":false,"imprecise_arg_kinds":false,"is_ellipsis_args":false,"name":"_frame_info_is_pyteal of StackFrame","ret_type":"builtins.bool","type_guard":null,"unpack_kwargs":false,"variables":[]}}}},"_frame_info_is_pyteal_import":{".class":"SymbolTableNode","kind":"Mdef","node":{".class":"Decorator","func":{".class":"FuncDef","abstract_status":0,"arg_kinds":[0,0],"arg_names":["cls","f"],"dataclass_transform_spec":null,"flags":["is_class","is_decorated"],"fullname":"pyteal.stack_frame.StackFrame._frame_info_is_pyteal_import","name":"_frame_info_is_pyteal_import","type":{".class":"CallableType","arg_kinds":[0,0],"arg_names":["cls","f"],"arg_types":[{".class":"TypeType","item":"pyteal.stack_frame.StackFrame"},{".class":"TypeAliasType","args":[],"type_ref":"inspect.FrameInfo"}],"bound_args":[],"def_extras":{"first_arg":"cls"},"fallback":"builtins.function","from_concatenate":false,"implicit":false,"imprecise_arg_kinds":false,"is_ellipsis_args":false,"name":"_frame_info_is_pyteal_import of StackFrame","ret_type":"builtins.bool","type_guard":null,"unpack_kwargs":false,"variables":[]}},"is_overload":false,"var":{".class":"Var","flags":["is_initialized_in_class","is_classmethod","is_ready","is_inferred"],"fullname":"pyteal.stack_frame.StackFrame._frame_info_is_pyteal_import","name":"_frame_info_is_pyteal_import","type":{".class":"CallableType","arg_kinds":[0,0],"arg_names":["cls","f"],"arg_types":[{".class":"TypeType","item":"pyteal.stack_frame.StackFrame"},{".class":"TypeAliasType","args":[],"type_ref":"inspect.FrameInfo"}],"bound_args":[],"def_extras":{"first_arg":"cls"},"fallback":"builtins.function","from_concatenate":false,"implicit":false,"imprecise_arg_kinds":false,"is_ellipsis_args":false,"name":"_frame_info_is_pyteal_import of StackFrame","ret_type":"builtins.bool","type_guard":null,"unpack_kwargs":false,"variables":[]}}}},"_frame_info_is_right_before_core":{".class":"SymbolTableNode","kind":"Mdef","node":{".class":"Decorator","func":{".class":"FuncDef","abstract_status":0,"arg_kinds":[0,0],"arg_names":["cls","f"],"dataclass_transform_spec":null,"flags":["is_class","is_decorated"],"fullname":"pyteal.stack_frame.StackFrame._frame_info_is_right_before_core","name":"_frame_info_is_right_before_core","type":{".class":"CallableType","arg_kinds":[0,0],"arg_names":["cls","f"],"arg_types":[{".class":"TypeType","item":"pyteal.stack_frame.StackFrame"},{".class":"TypeAliasType","args":[],"type_ref":"inspect.FrameInfo"}],"bound_args":[],"def_extras":{"first_arg":"cls"},"fallback":"builtins.function","from_concatenate":false,"implicit":false,"imprecise_arg_kinds":false,"is_ellipsis_args":false,"name":"_frame_info_is_right_before_core of StackFrame","ret_type":"builtins.bool","type_guard":null,"unpack_kwargs":false,"variables":[]}},"is_overload":false,"var":{".class":"Var","flags":["is_initialized_in_class","is_classmethod","is_ready","is_inferred"],"fullname":"pyteal.stack_frame.StackFrame._frame_info_is_right_before_core","name":"_frame_info_is_right_before_core","type":{".class":"CallableType","arg_kinds":[0,0],"arg_names":["cls","f"],"arg_types":[{".class":"TypeType","item":"pyteal.stack_frame.StackFrame"},{".class":"TypeAliasType","args":[],"type_ref":"inspect.FrameInfo"}],"bound_args":[],"def_extras":{"first_arg":"cls"},"fallback":"builtins.function","from_concatenate":false,"implicit":false,"imprecise_arg_kinds":false,"is_ellipsis_args":false,"name":"_frame_info_is_right_before_core of StackFrame","ret_type":"builtins.bool","type_guard":null,"unpack_kwargs":false,"variables":[]}}}},"_frame_info_not_py_crud":{".class":"SymbolTableNode","kind":"Mdef","node":{".class":"Decorator","func":{".class":"FuncDef","abstract_status":0,"arg_kinds":[0,0],"arg_names":["cls","f"],"dataclass_transform_spec":null,"flags":["is_class","is_decorated"],"fullname":"pyteal.stack_frame.StackFrame._frame_info_not_py_crud","name":"_frame_info_not_py_crud","type":{".class":"CallableType","arg_kinds":[0,0],"arg_names":["cls","f"],"arg_types":[{".class":"TypeType","item":"pyteal.stack_frame.StackFrame"},{".class":"TypeAliasType","args":[],"type_ref":"inspect.FrameInfo"}],"bound_args":[],"def_extras":{"first_arg":"cls"},"fallback":"builtins.function","from_concatenate":false,"implicit":false,"imprecise_arg_kinds":false,"is_ellipsis_args":false,"name":"_frame_info_not_py_crud of StackFrame","ret_type":"builtins.bool","type_guard":null,"unpack_kwargs":false,"variables":[]}},"is_overload":false,"var":{".class":"Var","flags":["is_initialized_in_class","is_classmethod","is_ready","is_inferred"],"fullname":"pyteal.stack_frame.StackFrame._frame_info_not_py_crud","name":"_frame_info_not_py_crud","type":{".class":"CallableType","arg_kinds":[0,0],"arg_names":["cls","f"],"arg_types":[{".class":"TypeType","item":"pyteal.stack_frame.StackFrame"},{".class":"TypeAliasType","args":[],"type_ref":"inspect.FrameInfo"}],"bound_args":[],"def_extras":{"first_arg":"cls"},"fallback":"builtins.function","from_concatenate":false,"implicit":false,"imprecise_arg_kinds":false,"is_ellipsis_args":false,"name":"_frame_info_not_py_crud of StackFrame","ret_type":"builtins.bool","type_guard":null,"unpack_kwargs":false,"variables":[]}}}},"_init_or_drop":{".class":"SymbolTableNode","kind":"Mdef","node":{".class":"Decorator","func":{".class":"FuncDef","abstract_status":0,"arg_kinds":[0,0,0,0],"arg_names":["cls","creator","f","full_stack"],"dataclass_transform_spec":null,"flags":["is_class","is_decorated"],"fullname":"pyteal.stack_frame.StackFrame._init_or_drop","name":"_init_or_drop","type":{".class":"CallableType","arg_kinds":[0,0,0,0],"arg_names":["cls","creator","f","full_stack"],"arg_types":[{".class":"TypeType","item":"pyteal.stack_frame.StackFrame"},"pyteal.stack_frame.NatalStackFrame",{".class":"TypeAliasType","args":[],"type_ref":"inspect.FrameInfo"},{".class":"Instance","args":[{".class":"TypeAliasType","args":[],"type_ref":"inspect.FrameInfo"}],"type_ref":"builtins.list"}],"bound_args":[],"def_extras":{"first_arg":"cls"},"fallback":"builtins.function","from_concatenate":false,"implicit":false,"imprecise_arg_kinds":false,"is_ellipsis_args":false,"name":"_init_or_drop of StackFrame","ret_type":{".class":"UnionType","items":["pyteal.stack_frame.StackFrame",{".class":"NoneType"}]},"type_guard":null,"unpack_kwargs":false,"variables":[]}},"is_overload":false,"var":{".class":"Var","flags":["is_initialized_in_class","is_classmethod","is_ready","is_inferred"],"fullname":"pyteal.stack_frame.StackFrame._init_or_drop","name":"_init_or_drop","type":{".class":"CallableType","arg_kinds":[0,0,0,0],"arg_names":["cls","creator","f","full_stack"],"arg_types":[{".class":"TypeType","item":"pyteal.stack_frame.StackFrame"},"pyteal.stack_frame.NatalStackFrame",{".class":"TypeAliasType","args":[],"type_ref":"inspect.FrameInfo"},{".class":"Instance","args":[{".class":"TypeAliasType","args":[],"type_ref":"inspect.FrameInfo"}],"type_ref":"builtins.list"}],"bound_args":[],"def_extras":{"first_arg":"cls"},"fallback":"builtins.function","from_concatenate":false,"implicit":false,"imprecise_arg_kinds":false,"is_ellipsis_args":false,"name":"_init_or_drop of StackFrame","ret_type":{".class":"UnionType","items":["pyteal.stack_frame.StackFrame",{".class":"NoneType"}]},"type_guard":null,"unpack_kwargs":false,"variables":[]}}}},"_internal_paths":{".class":"SymbolTableNode","kind":"Mdef","node":{".class":"Var","flags":["is_initialized_in_class","is_inferred","has_explicit_value"],"fullname":"pyteal.stack_frame.StackFrame._internal_paths","name":"_internal_paths","type":{".class":"Instance","args":["builtins.str"],"type_ref":"builtins.list"}}},"_internal_paths_re":{".class":"SymbolTableNode","kind":"Mdef","node":{".class":"Var","flags":["is_initialized_in_class","is_inferred","has_explicit_value"],"fullname":"pyteal.stack_frame.StackFrame._internal_paths_re","name":"_internal_paths_re","type":{".class":"Instance","args":["builtins.str"],"type_ref":"re.Pattern"}}},"_is_compilation_gateway":{".class":"SymbolTableNode","kind":"Mdef","node":{".class":"Decorator","func":{".class":"FuncDef","abstract_status":0,"arg_kinds":[0,0],"arg_names":["cls","f"],"dataclass_transform_spec":null,"flags":["is_class","is_decorated"],"fullname":"pyteal.stack_frame.StackFrame._is_compilation_gateway","name":"_is_compilation_gateway","type":{".class":"CallableType","arg_kinds":[0,0],"arg_names":["cls","f"],"arg_types":[{".class":"TypeType","item":"pyteal.stack_frame.StackFrame"},{".class":"TypeAliasType","args":[],"type_ref":"inspect.FrameInfo"}],"bound_args":[],"def_extras":{"first_arg":"cls"},"fallback":"builtins.function","from_concatenate":false,"implicit":false,"imprecise_arg_kinds":false,"is_ellipsis_args":false,"name":"_is_compilation_gateway of StackFrame","ret_type":"builtins.bool","type_guard":null,"unpack_kwargs":false,"variables":[]}},"is_overload":false,"var":{".class":"Var","flags":["is_initialized_in_class","is_classmethod","is_ready","is_inferred"],"fullname":"pyteal.stack_frame.StackFrame._is_compilation_gateway","name":"_is_compilation_gateway","type":{".class":"CallableType","arg_kinds":[0,0],"arg_names":["cls","f"],"arg_types":[{".class":"TypeType","item":"pyteal.stack_frame.StackFrame"},{".class":"TypeAliasType","args":[],"type_ref":"inspect.FrameInfo"}],"bound_args":[],"def_extras":{"first_arg":"cls"},"fallback":"builtins.function","from_concatenate":false,"implicit":false,"imprecise_arg_kinds":false,"is_ellipsis_args":false,"name":"_is_compilation_gateway of StackFrame","ret_type":"builtins.bool","type_guard":null,"unpack_kwargs":false,"variables":[]}}}},"_is_pyteal":{".class":"SymbolTableNode","kind":"Mdef","node":{".class":"FuncDef","abstract_status":0,"arg_kinds":[0],"arg_names":["self"],"dataclass_transform_spec":null,"flags":[],"fullname":"pyteal.stack_frame.StackFrame._is_pyteal","name":"_is_pyteal","type":{".class":"CallableType","arg_kinds":[0],"arg_names":["self"],"arg_types":["pyteal.stack_frame.StackFrame"],"bound_args":[],"def_extras":{"first_arg":"self"},"fallback":"builtins.function","from_concatenate":false,"implicit":false,"imprecise_arg_kinds":false,"is_ellipsis_args":false,"name":"_is_pyteal of StackFrame","ret_type":"builtins.bool","type_guard":null,"unpack_kwargs":false,"variables":[]}}},"_not_py_crud":{".class":"SymbolTableNode","kind":"Mdef","node":{".class":"FuncDef","abstract_status":0,"arg_kinds":[0],"arg_names":["self"],"dataclass_transform_spec":null,"flags":[],"fullname":"pyteal.stack_frame.StackFrame._not_py_crud","name":"_not_py_crud","type":{".class":"CallableType","arg_kinds":[0],"arg_names":["self"],"arg_types":["pyteal.stack_frame.StackFrame"],"bound_args":[],"def_extras":{"first_arg":"self"},"fallback":"builtins.function","from_concatenate":false,"implicit":false,"imprecise_arg_kinds":false,"is_ellipsis_args":false,"name":"_not_py_crud of StackFrame","ret_type":"builtins.bool","type_guard":null,"unpack_kwargs":false,"variables":[]}}},"as_pyteal_frame":{".class":"SymbolTableNode","kind":"Mdef","node":{".class":"FuncDef","abstract_status":0,"arg_kinds":[0],"arg_names":["self"],"dataclass_transform_spec":null,"flags":[],"fullname":"pyteal.stack_frame.StackFrame.as_pyteal_frame","name":"as_pyteal_frame","type":{".class":"CallableType","arg_kinds":[0],"arg_names":["self"],"arg_types":["pyteal.stack_frame.StackFrame"],"bound_args":[],"def_extras":{"first_arg":"self"},"fallback":"builtins.function","from_concatenate":false,"implicit":false,"imprecise_arg_kinds":false,"is_ellipsis_args":false,"name":"as_pyteal_frame of StackFrame","ret_type":"pyteal.stack_frame.PyTealFrame","type_guard":null,"unpack_kwargs":false,"variables":[]}}},"compiler_generated":{".class":"SymbolTableNode","kind":"Mdef","node":{".class":"FuncDef","abstract_status":0,"arg_kinds":[0],"arg_names":["self"],"dataclass_transform_spec":null,"flags":[],"fullname":"pyteal.stack_frame.StackFrame.compiler_generated","name":"compiler_generated","type":{".class":"CallableType","arg_kinds":[0],"arg_names":["self"],"arg_types":["pyteal.stack_frame.StackFrame"],"bound_args":[],"def_extras":{"first_arg":"self"},"fallback":"builtins.function","from_concatenate":false,"implicit":false,"imprecise_arg_kinds":false,"is_ellipsis_args":false,"name":"compiler_generated of StackFrame","ret_type":{".class":"UnionType","items":["builtins.bool",{".class":"NoneType"}]},"type_guard":null,"unpack_kwargs":false,"variables":[]}}},"creator":{".class":"SymbolTableNode","implicit":true,"kind":"Mdef","node":{".class":"Var","flags":["is_initialized_in_class","is_property","is_ready"],"fullname":"pyteal.stack_frame.StackFrame.creator","name":"creator","type":"pyteal.stack_frame.NatalStackFrame"}},"frame_info":{".class":"SymbolTableNode","implicit":true,"kind":"Mdef","node":{".class":"Var","flags":["is_initialized_in_class","is_property","is_ready"],"fullname":"pyteal.stack_frame.StackFrame.frame_info","name":"frame_info","type":{".class":"TypeAliasType","args":[],"type_ref":"inspect.FrameInfo"}}},"full_stack":{".class":"SymbolTableNode","kind":"Mdef","node":{".class":"Var","flags":["is_initialized_in_class","is_property","is_ready","has_explicit_value"],"fullname":"pyteal.stack_frame.StackFrame.full_stack","name":"full_stack","type":{".class":"UnionType","items":[{".class":"Instance","args":[{".class":"TypeAliasType","args":[],"type_ref":"inspect.FrameInfo"}],"type_ref":"builtins.list"},{".class":"NoneType"}]}}},"node":{".class":"SymbolTableNode","implicit":true,"kind":"Mdef","node":{".class":"Var","flags":["is_initialized_in_class","is_property","is_ready"],"fullname":"pyteal.stack_frame.StackFrame.node","name":"node","type":{".class":"UnionType","items":["_ast.AST",{".class":"NoneType"}]}}}},"self_type":{".class":"TypeVarType","default":{".class":"AnyType","missing_import_name":null,"source_any":null,"type_of_any":4},"fullname":"pyteal.stack_frame.StackFrame.Self","id":0,"name":"Self","namespace":"","upper_bound":"pyteal.stack_frame.StackFrame","values":[],"variance":0},"slots":null,"tuple_type":null,"type_vars":[],"typeddict_type":null}},"_PT_GEN":{".class":"SymbolTableNode","kind":"Gdef","node":{".class":"Var","flags":["is_inferred","has_explicit_value"],"fullname":"pyteal.stack_frame._PT_GEN","name":"_PT_GEN","type":{".class":"Instance","args":["builtins.str","builtins.str"],"type_ref":"builtins.dict"}}},"__annotations__":{".class":"SymbolTableNode","kind":"Gdef","node":{".class":"Var","flags":["is_ready"],"fullname":"pyteal.stack_frame.__annotations__","name":"__annotations__","type":{".class":"Instance","args":["builtins.str",{".class":"AnyType","missing_import_name":null,"source_any":null,"type_of_any":6}],"type_ref":"builtins.dict"}}},"__doc__":{".class":"SymbolTableNode","kind":"Gdef","node":{".class":"Var","flags":["is_ready"],"fullname":"pyteal.stack_frame.__doc__","name":"__doc__","type":"builtins.str"}},"__file__":{".class":"SymbolTableNode","kind":"Gdef","node":{".class":"Var","flags":["is_ready"],"fullname":"pyteal.stack_frame.__file__","name":"__file__","type":"builtins.str"}},"__name__":{".class":"SymbolTableNode","kind":"Gdef","node":{".class":"Var","flags":["is_ready"],"fullname":"pyteal.stack_frame.__name__","name":"__name__","type":"builtins.str"}},"__package__":{".class":"SymbolTableNode","kind":"Gdef","node":{".class":"Var","flags":["is_ready"],"fullname":"pyteal.stack_frame.__package__","name":"__package__","type":"builtins.str"}},"cast":{".class":"SymbolTableNode","cross_ref":"typing.cast","kind":"Gdef"},"contextmanager":{".class":"SymbolTableNode","cross_ref":"contextlib.contextmanager","kind":"Gdef"},"dataclass":{".class":"SymbolTableNode","cross_ref":"dataclasses.dataclass","kind":"Gdef"},"os":{".class":"SymbolTableNode","cross_ref":"os","kind":"Gdef"},"re":{".class":"SymbolTableNode","cross_ref":"re","kind":"Gdef"},"sourcemapping_off_context":{".class":"SymbolTableNode","kind":"Gdef","node":{".class":"Decorator","func":{".class":"FuncDef","abstract_status":0,"arg_kinds":[],"arg_names":[],"dataclass_transform_spec":null,"flags":["is_decorated"],"fullname":"pyteal.stack_frame.sourcemapping_off_context","name":"sourcemapping_off_context","type":null},"is_overload":false,"var":{".class":"Var","flags":["is_ready","is_inferred"],"fullname":"pyteal.stack_frame.sourcemapping_off_context","name":"sourcemapping_off_context","type":{".class":"CallableType","arg_kinds":[],"arg_names":[],"arg_types":[],"bound_args":[],"def_extras":{},"fallback":"builtins.function","from_concatenate":false,"implicit":false,"imprecise_arg_kinds":false,"is_ellipsis_args":false,"name":"sourcemapping_off_context","ret_type":{".class":"Instance","args":[{".class":"AnyType","missing_import_name":null,"source_any":{".class":"AnyType","missing_import_name":null,"source_any":null,"type_of_any":1},"type_of_any":7}],"type_ref":"contextlib._GeneratorContextManager"},"type_guard":null,"unpack_kwargs":false,"variables":[]}}}},"stack":{".class":"SymbolTableNode","cross_ref":"inspect.stack","kind":"Gdef"},"unparse":{".class":"SymbolTableNode","cross_ref":"ast.unparse","kind":"Gdef"}},"path":"c:\\Users\\HP\\anaconda3\\Lib\\site-packages\\pyteal\\stack_frame.py"}